{"horse":{"id":189,"name":"レディズビーク","sex":"牝","birth_year":2019,"birth_date":"2019年5月9日","color":"青鹿毛","status":"抹消","sire":"ドゥラメンテ","dam":"レディホークフィールド","broodmare_sire":"Hawk Wing","bms_line":"Northern Dancer","female_family":"F1-d","imported_foundation_mare":"レディホークフィールド(IRE) ～","pedigree_crosses":"Mr. Prospector(USA) ：S4×M4 Nijinsky(CAN) ：M5×M5","netkeiba_id":"2019105550","jbis_id":"0001312438","trainer":"池江泰寿","affiliation":"(栗 東)","trainer_region":"栗東","owner":"青芝商事","breeder":"ノーザンファーム","birthplace":"安平町","career_summary":"19戦1勝 [ 1-2-0-16 ]","major_win":"22'3歳未勝利","earnings_netkeiba":1725.6,"earnings_jbis":1725.6,"last_race":"2023 新潟 聖籠特別 １勝クラス","last_finish":2,"hkjc_name_zh":null,"name_en":"Ladies Beak","search_aliases":"Ladies Beak","achievement_class":"未勝利・新馬","dam_birth_date":null,"dam_birth_year":2006,"foal_birth_date":"2019-05-09","dam_age_at_foaling":13,"dam_age_precision":"year_only","foal_order":1,"dam_netkeiba_id":"000a013db7","dam_jbis_id":"0001225346","dam_career_summary":"0戦0勝 [ 0-0-0-0 ]","dam_earnings":0.0,"dam_major_win":null,"dam_known_foals":1,"dam_known_winners":1,"dam_known_graded_winners":0,"dam_siblings_json":"[]","dam_other_sire_foals_json":"[]","dam_metadata_source":"https://db.netkeiba.com/horse/000a013db7/","dam_metadata_status":"profile_fetched","owner_id":"831800","owner_color_url":"https://cdn.netkeiba.com/img//db/colours/831800.gif"},"sources":[{"source":"jbis","source_horse_id":"0001312438","url":"https://www.jbis.or.jp/horse/0001312438/","fetched_at":"2026-07-06T04:11:20.549323+00:00","data":{"affiliation":"(栗 東)","birth_year":2019,"breeder":"ノーザンファーム","breeder_url":"https://www.jbis.or.jp/breeder/0000002856/","bucket":"2019","dam":"レディホークフィールド(IRE)","dam_id":"0001225346","earnings":1725.6,"horse_id":"0001312438","horse_url":"https://www.jbis.or.jp/horse/0001312438/","last_finish":2,"last_race":"2023 新潟 聖籠特別 １勝クラス","last_race_url":"https://www.jbis.or.jp/race/result/20231029/104/09/","name":"レディズビーク","raw":["レディズビーク","2019","牝","レディホークフィールド(IRE)","池江 泰寿 (栗 東)","ノーザンファーム","1725.6万円","2023 新潟 聖籠特別 １勝クラス","2"],"sex":"牝","sire":"ドゥラメンテ","source":"jbis","source_url":"https://www.jbis.or.jp/horse/0001151936/sire/progeny/?year=2019&belong=0&sort=name&items=100&page=2&order=A","trainer":"池江 泰寿"}},{"source":"netkeiba","source_horse_id":"2019105550","url":"https://db.netkeiba.com/horse/2019105550/","fetched_at":"2026-07-06T04:11:20.549323+00:00","data":{"affiliation":"西","birth_year":2019,"breeder":"ノーザンファーム","broodmare_sire":"Hawk Wing","broodmare_sire_id":"000a010d4d","dam":"レディホークフィールド","dam_id":"000a013db7","earnings":1725.6,"horse_id":"2019105550","horse_url":"https://db.netkeiba.com/horse/2019105550/","name":"レディズビーク","owner":"青芝商事","raw":["","レディズビーク","牝","2019","[血] [掲] [写] [繁]","[西] 池江泰寿","ドゥラメンテ [ ]","レディホークフィールド [ ]","Hawk Wing [ ]","青芝商事","ノーザンファーム","1,725.6"],"sex":"牝","sire":"ドゥラメンテ","source":"netkeiba","source_url":"https://db.netkeiba.com/horse/list.html?sire_id=2012104511&range=all&page=10","trainer":"池江泰寿"}}],"races":[{"source":"netkeiba","race_date":"2024/03/23","meeting":"1中京5","weather":"雨","race_no":7,"race_name":"4歳以上1勝クラス","race_id":"202407010507","race_url":"https://db.netkeiba.com/race/202407010507/","field_size":14,"bracket":8,"horse_number":14,"odds":8.0,"popularity":3,"finish":9,"jockey":"団野大成","carried_weight":56.0,"surface":"芝","distance":"芝1600","distance_m":1600,"track_condition":"重","time":"1:37.3","margin":"0.7","corners":"78","pace":"91","last_3f":88.0,"body_weight":"96","winner_or_runner_up":"35.7","prize":null,"data":{"body_weight":"96","bracket":8,"carried_weight":56.0,"corners":"78","distance":"芝1600","distance_m":1600,"field_size":14,"finish":9,"horse_id":189,"horse_name":"レディズビーク","horse_number":14,"jockey":"団野大成","last_3f":88.0,"margin":"0.7","meeting":"1中京5","netkeiba_id":"2019105550","odds":8.0,"pace":"91","popularity":3,"prize":null,"race_date":"2024/03/23","race_id":"202407010507","race_name":"4歳以上1勝クラス","race_no":7,"race_url":"https://db.netkeiba.com/race/202407010507/","raw":["2024/03/23","1中京5","雨","7","4歳以上1勝クラス","","14","8","14","8.0","3","9","団野大成","56","芝1600","","重","8","1:37.3","0.7","78","78","91","88","96","9-9-9","36.2-36.2","35.7","464(0)","","","ビターグラッセ",""],"source":"netkeiba","surface":"芝","time":"1:37.3","track_condition":"重","weather":"雨","winner_or_runner_up":"35.7"}},{"source":"netkeiba","race_date":"2024/03/10","meeting":"1中京2","weather":"晴","race_no":7,"race_name":"4歳以上1勝クラス","race_id":"202407010207","race_url":"https://db.netkeiba.com/race/202407010207/","field_size":10,"bracket":3,"horse_number":3,"odds":14.8,"popularity":6,"finish":6,"jockey":"戸崎圭太","carried_weight":56.0,"surface":"芝","distance":"芝1600","distance_m":1600,"track_condition":"良","time":"1:34.3","margin":"0.4","corners":"**","pace":"**","last_3f":null,"body_weight":"**","winner_or_runner_up":"34.6","prize":null,"data":{"body_weight":"**","bracket":3,"carried_weight":56.0,"corners":"**","distance":"芝1600","distance_m":1600,"field_size":10,"finish":6,"horse_id":189,"horse_name":"レディズビーク","horse_number":3,"jockey":"戸崎圭太","last_3f":null,"margin":"0.4","meeting":"1中京2","netkeiba_id":"2019105550","odds":14.8,"pace":"**","popularity":6,"prize":null,"race_date":"2024/03/10","race_id":"202407010207","race_name":"4歳以上1勝クラス","race_no":7,"race_url":"https://db.netkeiba.com/race/202407010207/","raw":["2024/03/10","1中京2","晴","7","4歳以上1勝クラス","","10","3","3","14.8","6","6","戸崎圭太","56","芝1600","","良","**","1:34.3","0.4","**","**","**","**","**","7-6-6","35.6-34.8","34.6","464(-2)","","","アイルシャイン",""],"source":"netkeiba","surface":"芝","time":"1:34.3","track_condition":"良","weather":"晴","winner_or_runner_up":"34.6"}},{"source":"netkeiba","race_date":"2023/12/17","meeting":"4中京6","weather":"晴","race_no":6,"race_name":"3歳以上1勝クラス","race_id":"202307040606","race_url":"https://db.netkeiba.com/race/202307040606/","field_size":16,"bracket":2,"horse_number":4,"odds":5.7,"popularity":3,"finish":7,"jockey":"ドイル","carried_weight":56.0,"surface":"芝","distance":"芝1600","distance_m":1600,"track_condition":"良","time":"1:34.8","margin":"0.3","corners":"","pace":"","last_3f":null,"body_weight":"","winner_or_runner_up":"35.1","prize":null,"data":{"body_weight":"","bracket":2,"carried_weight":56.0,"corners":"","distance":"芝1600","distance_m":1600,"field_size":16,"finish":7,"horse_id":189,"horse_name":"レディズビーク","horse_number":4,"jockey":"ドイル","last_3f":null,"margin":"0.3","meeting":"4中京6","netkeiba_id":"2019105550","odds":5.7,"pace":"","popularity":3,"prize":null,"race_date":"2023/12/17","race_id":"202307040606","race_name":"3歳以上1勝クラス","race_no":6,"race_url":"https://db.netkeiba.com/race/202307040606/","raw":["2023/12/17","4中京6","晴","6","3歳以上1勝クラス","","16","2","4","5.7","3","7","ドイル","56","芝1600","","良","**","1:34.8","0.3","**","","","","","10-12-12","35.4-35.7","35.1","466(0)","","","ステラバルセロナ",""],"source":"netkeiba","surface":"芝","time":"1:34.8","track_condition":"良","weather":"晴","winner_or_runner_up":"35.1"}},{"source":"netkeiba","race_date":"2023/11/18","meeting":"5東京5","weather":"晴","race_no":12,"race_name":"3歳以上1勝クラス","race_id":"202305050512","race_url":"https://db.netkeiba.com/race/202305050512/","field_size":15,"bracket":5,"horse_number":9,"odds":83.9,"popularity":10,"finish":5,"jockey":"津村明秀","carried_weight":56.0,"surface":"芝","distance":"芝1600","distance_m":1600,"track_condition":"良","time":"1:33.2","margin":"0.7","corners":"","pace":"","last_3f":null,"body_weight":"","winner_or_runner_up":"35.1","prize":null,"data":{"body_weight":"","bracket":5,"carried_weight":56.0,"corners":"","distance":"芝1600","distance_m":1600,"field_size":15,"finish":5,"horse_id":189,"horse_name":"レディズビーク","horse_number":9,"jockey":"津村明秀","last_3f":null,"margin":"0.7","meeting":"5東京5","netkeiba_id":"2019105550","odds":83.9,"pace":"","popularity":10,"prize":null,"race_date":"2023/11/18","race_id":"202305050512","race_name":"3歳以上1勝クラス","race_no":12,"race_url":"https://db.netkeiba.com/race/202305050512/","raw":["2023/11/18","5東京5","晴","12","3歳以上1勝クラス","","15","5","9","83.9","10","5","津村明秀","56","芝1600","","良","**","1:33.2","0.7","**","","","","","5-5","34.8-34.9","35.1","466(-4)","","","エンデミズム","80.0"],"source":"netkeiba","surface":"芝","time":"1:33.2","track_condition":"良","weather":"晴","winner_or_runner_up":"35.1"}},{"source":"netkeiba","race_date":"2023/10/29","meeting":"4新潟6","weather":"雨","race_no":9,"race_name":"聖籠特別(1勝クラス)","race_id":"202304040609","race_url":"https://db.netkeiba.com/race/202304040609/","field_size":13,"bracket":1,"horse_number":1,"odds":9.4,"popularity":4,"finish":2,"jockey":"津村明秀","carried_weight":56.0,"surface":"芝","distance":"芝1800","distance_m":1800,"track_condition":"不","time":"1:51.1","margin":"0.2","corners":"","pace":"","last_3f":null,"body_weight":"","winner_or_runner_up":"35.4","prize":null,"data":{"body_weight":"","bracket":1,"carried_weight":56.0,"corners":"","distance":"芝1800","distance_m":1800,"field_size":13,"finish":2,"horse_id":189,"horse_name":"レディズビーク","horse_number":1,"jockey":"津村明秀","last_3f":null,"margin":"0.2","meeting":"4新潟6","netkeiba_id":"2019105550","odds":9.4,"pace":"","popularity":4,"prize":null,"race_date":"2023/10/29","race_id":"202304040609","race_name":"聖籠特別(1勝クラス)","race_no":9,"race_url":"https://db.netkeiba.com/race/202304040609/","raw":["2023/10/29","4新潟6","雨","9","聖籠特別(1勝クラス)","","13","1","1","9.4","4","2","津村明秀","56","芝1800","","不","**","1:51.1","0.2","**","","","","","8-6","37.6-35.7","35.4","470(+4)","","","ウィステリアリヴァ","450.6"],"source":"netkeiba","surface":"芝","time":"1:51.1","track_condition":"不","weather":"雨","winner_or_runner_up":"35.4"}},{"source":"netkeiba","race_date":"2023/10/14","meeting":"4新潟1","weather":"晴","race_no":7,"race_name":"3歳以上1勝クラス","race_id":"202304040107","race_url":"https://db.netkeiba.com/race/202304040107/","field_size":16,"bracket":3,"horse_number":5,"odds":11.7,"popularity":5,"finish":5,"jockey":"今村聖奈","carried_weight":53.0,"surface":"芝","distance":"芝2000","distance_m":2000,"track_condition":"良","time":"2:00.2","margin":"0.4","corners":"","pace":"","last_3f":null,"body_weight":"","winner_or_runner_up":"35.1","prize":null,"data":{"body_weight":"","bracket":3,"carried_weight":53.0,"corners":"","distance":"芝2000","distance_m":2000,"field_size":16,"finish":5,"horse_id":189,"horse_name":"レディズビーク","horse_number":5,"jockey":"今村聖奈","last_3f":null,"margin":"0.4","meeting":"4新潟1","netkeiba_id":"2019105550","odds":11.7,"pace":"","popularity":5,"prize":null,"race_date":"2023/10/14","race_id":"202304040107","race_name":"3歳以上1勝クラス","race_no":7,"race_url":"https://db.netkeiba.com/race/202304040107/","raw":["2023/10/14","4新潟1","晴","7","3歳以上1勝クラス","","16","3","5","11.7","5","5","今村聖奈","53","芝2000","","良","**","2:00.2","0.4","**","","","","","4-4","35.0-35.0","35.1","466(+6)","","","シュホ","80.0"],"source":"netkeiba","surface":"芝","time":"2:00.2","track_condition":"良","weather":"晴","winner_or_runner_up":"35.1"}},{"source":"netkeiba","race_date":"2023/07/29","meeting":"2新潟1","weather":"晴","race_no":9,"race_name":"出雲崎特別(1勝クラス)","race_id":"202304020109","race_url":"https://db.netkeiba.com/race/202304020109/","field_size":17,"bracket":4,"horse_number":7,"odds":172.2,"popularity":15,"finish":9,"jockey":"岩田望来","carried_weight":56.0,"surface":"芝","distance":"芝1800","distance_m":1800,"track_condition":"良","time":"1:46.0","margin":"0.6","corners":"","pace":"","last_3f":null,"body_weight":"","winner_or_runner_up":"34.5","prize":null,"data":{"body_weight":"","bracket":4,"carried_weight":56.0,"corners":"","distance":"芝1800","distance_m":1800,"field_size":17,"finish":9,"horse_id":189,"horse_name":"レディズビーク","horse_number":7,"jockey":"岩田望来","last_3f":null,"margin":"0.6","meeting":"2新潟1","netkeiba_id":"2019105550","odds":172.2,"pace":"","popularity":15,"prize":null,"race_date":"2023/07/29","race_id":"202304020109","race_name":"出雲崎特別(1勝クラス)","race_no":9,"race_url":"https://db.netkeiba.com/race/202304020109/","raw":["2023/07/29","2新潟1","晴","9","出雲崎特別(1勝クラス)","","17","4","7","172.2","15","9","岩田望来","56","芝1800","","良","**","1:46.0","0.6","**","","","","","4-5","34.7-34.3","34.5","460(+2)","","","トーホウガレオン",""],"source":"netkeiba","surface":"芝","time":"1:46.0","track_condition":"良","weather":"晴","winner_or_runner_up":"34.5"}},{"source":"netkeiba","race_date":"2023/05/14","meeting":"1京都8","weather":"小雨","race_no":6,"race_name":"4歳以上1勝クラス","race_id":"202308010806","race_url":"https://db.netkeiba.com/race/202308010806/","field_size":8,"bracket":8,"horse_number":8,"odds":17.4,"popularity":6,"finish":7,"jockey":"藤岡康太","carried_weight":56.0,"surface":"芝","distance":"芝1800","distance_m":1800,"track_condition":"稍","time":"1:49.1","margin":"1.7","corners":"","pace":"","last_3f":null,"body_weight":"","winner_or_runner_up":"36.6","prize":null,"data":{"body_weight":"","bracket":8,"carried_weight":56.0,"corners":"","distance":"芝1800","distance_m":1800,"field_size":8,"finish":7,"horse_id":189,"horse_name":"レディズビーク","horse_number":8,"jockey":"藤岡康太","last_3f":null,"margin":"1.7","meeting":"1京都8","netkeiba_id":"2019105550","odds":17.4,"pace":"","popularity":6,"prize":null,"race_date":"2023/05/14","race_id":"202308010806","race_name":"4歳以上1勝クラス","race_no":6,"race_url":"https://db.netkeiba.com/race/202308010806/","raw":["2023/05/14","1京都8","小雨","6","4歳以上1勝クラス","","8","8","8","17.4","6","7","藤岡康太","56","芝1800","","稍","**","1:49.1","1.7","**","","","","","8-8","35.4-35.9","36.6","458(+16)","","","サンクフィーユ",""],"source":"netkeiba","surface":"芝","time":"1:49.1","track_condition":"稍","weather":"小雨","winner_or_runner_up":"36.6"}},{"source":"netkeiba","race_date":"2023/03/19","meeting":"2中京4","weather":"晴","race_no":6,"race_name":"4歳以上1勝クラス","race_id":"202307020406","race_url":"https://db.netkeiba.com/race/202307020406/","field_size":16,"bracket":5,"horse_number":10,"odds":29.2,"popularity":11,"finish":8,"jockey":"荻野極","carried_weight":56.0,"surface":"芝","distance":"芝1600","distance_m":1600,"track_condition":"稍","time":"1:36.6","margin":"0.8","corners":"","pace":"","last_3f":null,"body_weight":"","winner_or_runner_up":"35.0","prize":null,"data":{"body_weight":"","bracket":5,"carried_weight":56.0,"corners":"","distance":"芝1600","distance_m":1600,"field_size":16,"finish":8,"horse_id":189,"horse_name":"レディズビーク","horse_number":10,"jockey":"荻野極","last_3f":null,"margin":"0.8","meeting":"2中京4","netkeiba_id":"2019105550","odds":29.2,"pace":"","popularity":11,"prize":null,"race_date":"2023/03/19","race_id":"202307020406","race_name":"4歳以上1勝クラス","race_no":6,"race_url":"https://db.netkeiba.com/race/202307020406/","raw":["2023/03/19","2中京4","晴","6","4歳以上1勝クラス","","16","5","10","29.2","11","8","荻野極","56","芝1600","","稍","**","1:36.6","0.8","**","","","","","10-8-7","36.1-35.1","35.0","442(+4)","","","ダノンソフィア",""],"source":"netkeiba","surface":"芝","time":"1:36.6","track_condition":"稍","weather":"晴","winner_or_runner_up":"35.0"}},{"source":"netkeiba","race_date":"2023/02/18","meeting":"2小倉3","weather":"曇","race_no":8,"race_name":"4歳以上1勝クラス","race_id":"202310020308","race_url":"https://db.netkeiba.com/race/202310020308/","field_size":16,"bracket":8,"horse_number":15,"odds":5.6,"popularity":3,"finish":null,"jockey":"今村聖奈","carried_weight":52.0,"surface":"芝","distance":"芝1800","distance_m":1800,"track_condition":"稍","time":"","margin":"","corners":"","pace":"","last_3f":null,"body_weight":"","winner_or_runner_up":"","prize":null,"data":{"body_weight":"","bracket":8,"carried_weight":52.0,"corners":"","distance":"芝1800","distance_m":1800,"field_size":16,"finish":null,"horse_id":189,"horse_name":"レディズビーク","horse_number":15,"jockey":"今村聖奈","last_3f":null,"margin":"","meeting":"2小倉3","netkeiba_id":"2019105550","odds":5.6,"pace":"","popularity":3,"prize":null,"race_date":"2023/02/18","race_id":"202310020308","race_name":"4歳以上1勝クラス","race_no":8,"race_url":"https://db.netkeiba.com/race/202310020308/","raw":["2023/02/18","2小倉3","曇","8","4歳以上1勝クラス","","16","8","15","5.6","3","中","今村聖奈","52","芝1800","","稍","**","","","**","","","","","5-6-4-9","37.9-36.2","","438(-6)","","","ロムネヤ",""],"source":"netkeiba","surface":"芝","time":"","track_condition":"稍","weather":"曇","winner_or_runner_up":""}},{"source":"netkeiba","race_date":"2022/12/17","meeting":"6中京5","weather":"曇","race_no":6,"race_name":"3歳以上1勝クラス","race_id":"202207060506","race_url":"https://db.netkeiba.com/race/202207060506/","field_size":15,"bracket":5,"horse_number":8,"odds":21.9,"popularity":9,"finish":4,"jockey":"今村聖奈","carried_weight":51.0,"surface":"芝","distance":"芝1600","distance_m":1600,"track_condition":"良","time":"1:34.7","margin":"0.2","corners":"","pace":"","last_3f":null,"body_weight":"","winner_or_runner_up":"34.3","prize":null,"data":{"body_weight":"","bracket":5,"carried_weight":51.0,"corners":"","distance":"芝1600","distance_m":1600,"field_size":15,"finish":4,"horse_id":189,"horse_name":"レディズビーク","horse_number":8,"jockey":"今村聖奈","last_3f":null,"margin":"0.2","meeting":"6中京5","netkeiba_id":"2019105550","odds":21.9,"pace":"","popularity":9,"prize":null,"race_date":"2022/12/17","race_id":"202207060506","race_name":"3歳以上1勝クラス","race_no":6,"race_url":"https://db.netkeiba.com/race/202207060506/","raw":["2022/12/17","6中京5","曇","6","3歳以上1勝クラス","","15","5","8","21.9","9","4","今村聖奈","51","芝1600","","良","**","1:34.7","0.2","**","","","","","13-11-11","35.3-35.1","34.3","444(-6)","","","パンドレア","120.0"],"source":"netkeiba","surface":"芝","time":"1:34.7","track_condition":"良","weather":"曇","winner_or_runner_up":"34.3"}},{"source":"netkeiba","race_date":"2022/11/19","meeting":"5阪神5","weather":"晴","race_no":7,"race_name":"3歳以上1勝クラス","race_id":"202209050507","race_url":"https://db.netkeiba.com/race/202209050507/","field_size":11,"bracket":3,"horse_number":3,"odds":17.3,"popularity":4,"finish":10,"jockey":"今村聖奈","carried_weight":50.0,"surface":"ダ","distance":"ダ1800","distance_m":1800,"track_condition":"良","time":"1:56.4","margin":"3.0","corners":"","pace":"","last_3f":null,"body_weight":"","winner_or_runner_up":"38.5","prize":null,"data":{"body_weight":"","bracket":3,"carried_weight":50.0,"corners":"","distance":"ダ1800","distance_m":1800,"field_size":11,"finish":10,"horse_id":189,"horse_name":"レディズビーク","horse_number":3,"jockey":"今村聖奈","last_3f":null,"margin":"3.0","meeting":"5阪神5","netkeiba_id":"2019105550","odds":17.3,"pace":"","popularity":4,"prize":null,"race_date":"2022/11/19","race_id":"202209050507","race_name":"3歳以上1勝クラス","race_no":7,"race_url":"https://db.netkeiba.com/race/202209050507/","raw":["2022/11/19","5阪神5","晴","7","3歳以上1勝クラス","","11","3","3","17.3","4","10","今村聖奈","50","ダ1800","","良","**","1:56.4","3.0","**","","","","","10-11-11-11","37.2-37.0","38.5","450(-12)","","","プレミアムスマイル",""],"source":"netkeiba","surface":"ダ","time":"1:56.4","track_condition":"良","weather":"晴","winner_or_runner_up":"38.5"}},{"source":"netkeiba","race_date":"2022/08/28","meeting":"2札幌6","weather":"晴","race_no":8,"race_name":"3歳以上1勝クラス","race_id":"202201020608","race_url":"https://db.netkeiba.com/race/202201020608/","field_size":14,"bracket":4,"horse_number":5,"odds":6.3,"popularity":3,"finish":14,"jockey":"松山弘平","carried_weight":52.0,"surface":"芝","distance":"芝1500","distance_m":1500,"track_condition":"良","time":"1:31.0","margin":"1.4","corners":"","pace":"","last_3f":null,"body_weight":"","winner_or_runner_up":"36.0","prize":null,"data":{"body_weight":"","bracket":4,"carried_weight":52.0,"corners":"","distance":"芝1500","distance_m":1500,"field_size":14,"finish":14,"horse_id":189,"horse_name":"レディズビーク","horse_number":5,"jockey":"松山弘平","last_3f":null,"margin":"1.4","meeting":"2札幌6","netkeiba_id":"2019105550","odds":6.3,"pace":"","popularity":3,"prize":null,"race_date":"2022/08/28","race_id":"202201020608","race_name":"3歳以上1勝クラス","race_no":8,"race_url":"https://db.netkeiba.com/race/202201020608/","raw":["2022/08/28","2札幌6","晴","8","3歳以上1勝クラス","","14","4","5","6.3","3","14","松山弘平","52","芝1500","","良","**","1:31.0","1.4","**","","","","","4-3-6","30.7-35.0","36.0","462(+6)","","","アグリ",""],"source":"netkeiba","surface":"芝","time":"1:31.0","track_condition":"良","weather":"晴","winner_or_runner_up":"36.0"}},{"source":"netkeiba","race_date":"2022/08/06","meeting":"1札幌5","weather":"晴","race_no":12,"race_name":"3歳以上1勝クラス","race_id":"202201010512","race_url":"https://db.netkeiba.com/race/202201010512/","field_size":14,"bracket":3,"horse_number":3,"odds":6.0,"popularity":4,"finish":5,"jockey":"角田大和","carried_weight":50.0,"surface":"芝","distance":"芝1500","distance_m":1500,"track_condition":"良","time":"1:29.4","margin":"0.1","corners":"","pace":"","last_3f":null,"body_weight":"","winner_or_runner_up":"34.7","prize":null,"data":{"body_weight":"","bracket":3,"carried_weight":50.0,"corners":"","distance":"芝1500","distance_m":1500,"field_size":14,"finish":5,"horse_id":189,"horse_name":"レディズビーク","horse_number":3,"jockey":"角田大和","last_3f":null,"margin":"0.1","meeting":"1札幌5","netkeiba_id":"2019105550","odds":6.0,"pace":"","popularity":4,"prize":null,"race_date":"2022/08/06","race_id":"202201010512","race_name":"3歳以上1勝クラス","race_no":12,"race_url":"https://db.netkeiba.com/race/202201010512/","raw":["2022/08/06","1札幌5","晴","12","3歳以上1勝クラス","","14","3","3","6.0","4","5","角田大和","50","芝1500","","良","**","1:29.4","0.1","**","","","","","6-7-5","30.1-35.0","34.7","456(+20)","","","エープラス","77.0"],"source":"netkeiba","surface":"芝","time":"1:29.4","track_condition":"良","weather":"晴","winner_or_runner_up":"34.7"}},{"source":"netkeiba","race_date":"2022/06/05","meeting":"4中京2","weather":"晴","race_no":6,"race_name":"3歳未勝利","race_id":"202207040206","race_url":"https://db.netkeiba.com/race/202207040206/","field_size":16,"bracket":3,"horse_number":5,"odds":6.2,"popularity":4,"finish":1,"jockey":"今村聖奈","carried_weight":50.0,"surface":"芝","distance":"芝1600","distance_m":1600,"track_condition":"良","time":"1:34.1","margin":"-0.1","corners":"","pace":"","last_3f":null,"body_weight":"","winner_or_runner_up":"35.3","prize":null,"data":{"body_weight":"","bracket":3,"carried_weight":50.0,"corners":"","distance":"芝1600","distance_m":1600,"field_size":16,"finish":1,"horse_id":189,"horse_name":"レディズビーク","horse_number":5,"jockey":"今村聖奈","last_3f":null,"margin":"-0.1","meeting":"4中京2","netkeiba_id":"2019105550","odds":6.2,"pace":"","popularity":4,"prize":null,"race_date":"2022/06/05","race_id":"202207040206","race_name":"3歳未勝利","race_no":6,"race_url":"https://db.netkeiba.com/race/202207040206/","raw":["2022/06/05","4中京2","晴","6","3歳未勝利","","16","3","5","6.2","4","1","今村聖奈","50","芝1600","","良","**","1:34.1","-0.1","**","","","","","6-3-3","35.0-35.7","35.3","436(0)","","","(アオイゴールドワン)","520.0"],"source":"netkeiba","surface":"芝","time":"1:34.1","track_condition":"良","weather":"晴","winner_or_runner_up":"35.3"}},{"source":"netkeiba","race_date":"2022/05/14","meeting":"1新潟3","weather":"曇","race_no":2,"race_name":"3歳未勝利","race_id":"202204010302","race_url":"https://db.netkeiba.com/race/202204010302/","field_size":13,"bracket":7,"horse_number":10,"odds":4.1,"popularity":2,"finish":2,"jockey":"今村聖奈","carried_weight":50.0,"surface":"芝","distance":"芝1800","distance_m":1800,"track_condition":"稍","time":"1:49.3","margin":"0.1","corners":"","pace":"","last_3f":null,"body_weight":"","winner_or_runner_up":"35.4","prize":null,"data":{"body_weight":"","bracket":7,"carried_weight":50.0,"corners":"","distance":"芝1800","distance_m":1800,"field_size":13,"finish":2,"horse_id":189,"horse_name":"レディズビーク","horse_number":10,"jockey":"今村聖奈","last_3f":null,"margin":"0.1","meeting":"1新潟3","netkeiba_id":"2019105550","odds":4.1,"pace":"","popularity":2,"prize":null,"race_date":"2022/05/14","race_id":"202204010302","race_name":"3歳未勝利","race_no":2,"race_url":"https://db.netkeiba.com/race/202204010302/","raw":["2022/05/14","1新潟3","曇","2","3歳未勝利","","13","7","10","4.1","2","2","今村聖奈","50","芝1800","","稍","**","1:49.3","0.1","**","","","","","5-5","36.5-35.6","35.4","436(+6)","","","バトルキャット","210.0"],"source":"netkeiba","surface":"芝","time":"1:49.3","track_condition":"稍","weather":"曇","winner_or_runner_up":"35.4"}},{"source":"netkeiba","race_date":"2022/04/24","meeting":"2阪神10","weather":"小雨","race_no":4,"race_name":"3歳未勝利","race_id":"202209021004","race_url":"https://db.netkeiba.com/race/202209021004/","field_size":18,"bracket":3,"horse_number":5,"odds":20.8,"popularity":6,"finish":4,"jockey":"今村聖奈","carried_weight":50.0,"surface":"芝","distance":"芝1600","distance_m":1600,"track_condition":"稍","time":"1:36.8","margin":"0.6","corners":"","pace":"","last_3f":null,"body_weight":"","winner_or_runner_up":"35.0","prize":null,"data":{"body_weight":"","bracket":3,"carried_weight":50.0,"corners":"","distance":"芝1600","distance_m":1600,"field_size":18,"finish":4,"horse_id":189,"horse_name":"レディズビーク","horse_number":5,"jockey":"今村聖奈","last_3f":null,"margin":"0.6","meeting":"2阪神10","netkeiba_id":"2019105550","odds":20.8,"pace":"","popularity":6,"prize":null,"race_date":"2022/04/24","race_id":"202209021004","race_name":"3歳未勝利","race_no":4,"race_url":"https://db.netkeiba.com/race/202209021004/","raw":["2022/04/24","2阪神10","小雨","4","3歳未勝利","","18","3","5","20.8","6","4","今村聖奈","50","芝1600","","稍","**","1:36.8","0.6","**","","","","","4-5","36.1-34.9","35.0","430(-8)","","","コスタボニータ","78.0"],"source":"netkeiba","surface":"芝","time":"1:36.8","track_condition":"稍","weather":"小雨","winner_or_runner_up":"35.0"}},{"source":"netkeiba","race_date":"2022/01/15","meeting":"1中京5","weather":"曇","race_no":5,"race_name":"3歳未勝利","race_id":"202207010505","race_url":"https://db.netkeiba.com/race/202207010505/","field_size":18,"bracket":8,"horse_number":16,"odds":14.6,"popularity":5,"finish":12,"jockey":"団野大成","carried_weight":54.0,"surface":"芝","distance":"芝1400","distance_m":1400,"track_condition":"良","time":"1:23.2","margin":"1.6","corners":"","pace":"","last_3f":null,"body_weight":"","winner_or_runner_up":"36.4","prize":null,"data":{"body_weight":"","bracket":8,"carried_weight":54.0,"corners":"","distance":"芝1400","distance_m":1400,"field_size":18,"finish":12,"horse_id":189,"horse_name":"レディズビーク","horse_number":16,"jockey":"団野大成","last_3f":null,"margin":"1.6","meeting":"1中京5","netkeiba_id":"2019105550","odds":14.6,"pace":"","popularity":5,"prize":null,"race_date":"2022/01/15","race_id":"202207010505","race_name":"3歳未勝利","race_no":5,"race_url":"https://db.netkeiba.com/race/202207010505/","raw":["2022/01/15","1中京5","曇","5","3歳未勝利","","18","8","16","14.6","5","12","団野大成","54","芝1400","","良","**","1:23.2","1.6","**","","","","","12-12","33.9-35.9","36.4","438(-10)","","","ショウナンハクラク",""],"source":"netkeiba","surface":"芝","time":"1:23.2","track_condition":"良","weather":"曇","winner_or_runner_up":"36.4"}},{"source":"netkeiba","race_date":"2021/11/21","meeting":"5阪神6","weather":"晴","race_no":4,"race_name":"2歳新馬","race_id":"202109050604","race_url":"https://db.netkeiba.com/race/202109050604/","field_size":16,"bracket":6,"horse_number":12,"odds":13.4,"popularity":5,"finish":4,"jockey":"横山武史","carried_weight":54.0,"surface":"芝","distance":"芝1600","distance_m":1600,"track_condition":"良","time":"1:35.0","margin":"0.3","corners":"","pace":"","last_3f":null,"body_weight":"","winner_or_runner_up":"34.9","prize":null,"data":{"body_weight":"","bracket":6,"carried_weight":54.0,"corners":"","distance":"芝1600","distance_m":1600,"field_size":16,"finish":4,"horse_id":189,"horse_name":"レディズビーク","horse_number":12,"jockey":"横山武史","last_3f":null,"margin":"0.3","meeting":"5阪神6","netkeiba_id":"2019105550","odds":13.4,"pace":"","popularity":5,"prize":null,"race_date":"2021/11/21","race_id":"202109050604","race_name":"2歳新馬","race_no":4,"race_url":"https://db.netkeiba.com/race/202109050604/","raw":["2021/11/21","5阪神6","晴","4","2歳新馬","","16","6","12","13.4","5","4","横山武史","54","芝1600","","良","**","1:35.0","0.3","**","","","","","1-1","35.6-34.6","34.9","448(0)","","","アストロフィライト","110.0"],"source":"netkeiba","surface":"芝","time":"1:35.0","track_condition":"良","weather":"晴","winner_or_runner_up":"34.9"}}],"stud":[{"id":200,"role":"broodmare","studbook_url":"https://www.studbook.jp/users/ja/Honba?hid=3344223590516","own_netkeiba_url":null,"external_links_json":null,"source_name":"Japan Stud Book","note":"父ドゥラメンテの繁殖登録馬。","fees":[],"stallion_stats":[],"coverings":[{"cover_year":2025,"cover_date":"2025. 4.26","due_date":"2026. 3.26","stallion_name":"キタサンブラック（ＪＰＮ）","keeper_location":"北海道浦河郡浦河町","keeper_name":"辻牧場"},{"cover_year":2024,"cover_date":"2024. 4.21","due_date":"2025. 3.21","stallion_name":"キズナ（ＪＰＮ）","keeper_location":"北海道勇払郡安平町","keeper_name":"ノーザンファーム"}],"foals":[{"result_year":2026,"birth_date":"2026. 4. 6","color":"鹿","sex":"♂","foal_name":"","sire_name":"キタサンブラック（ＪＰＮ）","note":"産駒は血統登録申込をされていません"},{"result_year":2025,"birth_date":"2025. 4. 1","color":"黒鹿","sex":"♀","foal_name":"馬名未登録","sire_name":"キズナ（ＪＰＮ）","note":null}],"news":[]}]}