{"horse":{"id":311,"name":"オウケンミッキー","sex":"牝","birth_year":2019,"birth_date":"2019年4月28日","color":"鹿毛","status":"牝","sire":"ドゥラメンテ","dam":"オウケンハナミズキ","broodmare_sire":"バゴ","bms_line":"Nasrullah","female_family":"F14-c","imported_foundation_mare":"デュプレ(GB) ～","pedigree_crosses":"Mr. Prospector(USA) ：S4×M5 Halo(USA) ：S4×M5 Nureyev(USA) ：M4×S5","netkeiba_id":"2019103828","jbis_id":"0001308804","trainer":"瀬戸幸一","affiliation":"(水 沢)","trainer_region":"地方","owner":"後藤順男","breeder":"辻牧場","birthplace":"浦河町","career_summary":"33戦1勝 [ 1-2-3-27 ]","major_win":"C2四組","earnings_netkeiba":612.5,"earnings_jbis":612.5,"last_race":"","last_finish":null,"hkjc_name_zh":null,"name_en":"Oken Mickey","search_aliases":"Oken Mickey","achievement_class":"地方・その他","dam_birth_date":"2009-03-25","dam_birth_year":2009,"foal_birth_date":"2019-04-28","dam_age_at_foaling":10,"dam_age_precision":"exact","foal_order":1,"dam_netkeiba_id":"2009100106","dam_jbis_id":"0001110627","dam_career_summary":"28戦1勝 [ 1-2-1-24 ]","dam_earnings":1450.0,"dam_major_win":"11'2歳未勝利","dam_known_foals":1,"dam_known_winners":1,"dam_known_graded_winners":0,"dam_siblings_json":"[]","dam_other_sire_foals_json":"[]","dam_metadata_source":"https://db.netkeiba.com/horse/2009100106/","dam_metadata_status":"profile_fetched","owner_id":"x09065","owner_color_url":null,"dam_biological_parity":4,"dam_registered_foal_order":4,"dam_covering_sequence":null,"parity_confidence":"high","parity_source_url":"https://www.studbook.jp/users/ja/SearchBameiList?initial_forward=%E3%82%AA%E3%82%A6%E3%82%B1%E3%83%B3%E3%83%8F%E3%83%8A%E3%83%9F%E3%82%BA%E3%82%AD&submit=%E9%A6%AC%E5%90%8D%E6%A4%9C%E7%B4%A2","dam_parity_basis":"biological_and_registered","parity_source_name":"Japan Stud Book"},"sources":[{"source":"jbis","source_horse_id":"0001308804","url":"https://www.jbis.or.jp/horse/0001308804/","fetched_at":"2026-07-06T04:11:20.549323+00:00","data":{"affiliation":"(水 沢)","birth_year":2019,"breeder":"辻 牧場","breeder_url":"https://www.jbis.or.jp/breeder/0000000189/","bucket":"2019","dam":"オウケンハナミズキ","dam_id":"0001110627","earnings":612.5,"horse_id":"0001308804","horse_url":"https://www.jbis.or.jp/horse/0001308804/","last_finish":null,"last_race":"","last_race_url":null,"name":"オウケンミッキー","raw":["オウケンミッキー","2019","牝","オウケンハナミズキ","瀬戸 幸一 (水 沢)","辻 牧場","612.5万円","",""],"sex":"牝","sire":"ドゥラメンテ","source":"jbis","source_url":"https://www.jbis.or.jp/horse/0001151936/sire/progeny/?year=2019&belong=0&sort=name&items=100&page=1&order=A","trainer":"瀬戸 幸一"}},{"source":"netkeiba","source_horse_id":"2019103828","url":"https://db.netkeiba.com/horse/2019103828/","fetched_at":"2026-07-06T04:11:20.549323+00:00","data":{"affiliation":"地","birth_year":2019,"breeder":"辻牧場","broodmare_sire":"バゴ","broodmare_sire_id":"2001190004","dam":"オウケンハナミズキ","dam_id":"2009100106","earnings":612.5,"horse_id":"2019103828","horse_url":"https://db.netkeiba.com/horse/2019103828/","name":"オウケンミッキー","owner":"後藤順男","raw":["","オウケンミッキー","牝","2019","[血] [掲] [写]","[地] 瀬戸幸一","ドゥラメンテ [ ]","オウケンハナミズキ [ ]","バゴ [ ]","後藤順男","辻牧場","612.5"],"sex":"牝","sire":"ドゥラメンテ","source":"netkeiba","source_url":"https://db.netkeiba.com/horse/list.html?sire_id=2012104511&range=all&page=16","trainer":"瀬戸幸一"}}],"races":[{"source":"netkeiba","race_date":"2023/12/18","meeting":"水沢","weather":"","race_no":2,"race_name":"C2","race_id":"202336121802","race_url":"https://db.netkeiba.com/race/202336121802/","field_size":0,"bracket":7,"horse_number":8,"odds":null,"popularity":null,"finish":null,"jockey":"佐々木志","carried_weight":52.0,"surface":"ダ","distance":"ダ850","distance_m":850,"track_condition":"","time":"","margin":"","corners":"","pace":"","last_3f":null,"body_weight":"","winner_or_runner_up":"","prize":null,"data":{"body_weight":"","bracket":7,"carried_weight":52.0,"corners":"","distance":"ダ850","distance_m":850,"field_size":0,"finish":null,"horse_id":311,"horse_name":"オウケンミッキー","horse_number":8,"jockey":"佐々木志","last_3f":null,"margin":"","meeting":"水沢","netkeiba_id":"2019103828","odds":null,"pace":"","popularity":null,"prize":null,"race_date":"2023/12/18","race_id":"202336121802","race_name":"C2","race_no":2,"race_url":"https://db.netkeiba.com/race/202336121802/","raw":["2023/12/18","水沢","","2","C2","","0","7","8","","","","佐々木志","52","ダ850","","","","","","","","","","","","","","計不","","","",""],"source":"netkeiba","surface":"ダ","time":"","track_condition":"","weather":"","winner_or_runner_up":""}},{"source":"netkeiba","race_date":"2023/12/11","meeting":"水沢","weather":"晴","race_no":4,"race_name":"オッズパークテシオブ(C2)","race_id":"202336121104","race_url":"https://db.netkeiba.com/race/202336121104/","field_size":11,"bracket":2,"horse_number":2,"odds":82.2,"popularity":9,"finish":11,"jockey":"塚本涼人","carried_weight":54.0,"surface":"ダ","distance":"ダ1300","distance_m":1300,"track_condition":"稍","time":"1:26.7","margin":"3.2","corners":"","pace":"","last_3f":null,"body_weight":"","winner_or_runner_up":"40.9","prize":null,"data":{"body_weight":"","bracket":2,"carried_weight":54.0,"corners":"","distance":"ダ1300","distance_m":1300,"field_size":11,"finish":11,"horse_id":311,"horse_name":"オウケンミッキー","horse_number":2,"jockey":"塚本涼人","last_3f":null,"margin":"3.2","meeting":"水沢","netkeiba_id":"2019103828","odds":82.2,"pace":"","popularity":9,"prize":null,"race_date":"2023/12/11","race_id":"202336121104","race_name":"オッズパークテシオブ(C2)","race_no":4,"race_url":"https://db.netkeiba.com/race/202336121104/","raw":["2023/12/11","水沢","晴","4","オッズパークテシオブ(C2)","","11","2","2","82.2","9","11","塚本涼人","54","ダ1300","","稍","**","1:26.7","3.2","**","","","","","8-8-10-11","","40.9","446(-16)","","","ヤマニントナーダ",""],"source":"netkeiba","surface":"ダ","time":"1:26.7","track_condition":"稍","weather":"晴","winner_or_runner_up":"40.9"}},{"source":"netkeiba","race_date":"2023/12/04","meeting":"水沢","weather":"晴","race_no":5,"race_name":"C2五組","race_id":"202336120405","race_url":"https://db.netkeiba.com/race/202336120405/","field_size":11,"bracket":2,"horse_number":2,"odds":29.0,"popularity":7,"finish":10,"jockey":"佐々木志","carried_weight":52.0,"surface":"ダ","distance":"ダ1400","distance_m":1400,"track_condition":"重","time":"1:32.1","margin":"2.9","corners":"","pace":"","last_3f":null,"body_weight":"","winner_or_runner_up":"42.2","prize":null,"data":{"body_weight":"","bracket":2,"carried_weight":52.0,"corners":"","distance":"ダ1400","distance_m":1400,"field_size":11,"finish":10,"horse_id":311,"horse_name":"オウケンミッキー","horse_number":2,"jockey":"佐々木志","last_3f":null,"margin":"2.9","meeting":"水沢","netkeiba_id":"2019103828","odds":29.0,"pace":"","popularity":7,"prize":null,"race_date":"2023/12/04","race_id":"202336120405","race_name":"C2五組","race_no":5,"race_url":"https://db.netkeiba.com/race/202336120405/","raw":["2023/12/04","水沢","晴","5","C2五組","","11","2","2","29.0","7","10","佐々木志","52","ダ1400","","重","**","1:32.1","2.9","**","","","","","2-2-4-7","","42.2","462(+9)","","","ブレガーロード",""],"source":"netkeiba","surface":"ダ","time":"1:32.1","track_condition":"重","weather":"晴","winner_or_runner_up":"42.2"}},{"source":"netkeiba","race_date":"2023/11/27","meeting":"水沢","weather":"曇","race_no":5,"race_name":"C2四組","race_id":"202336112705","race_url":"https://db.netkeiba.com/race/202336112705/","field_size":10,"bracket":3,"horse_number":3,"odds":null,"popularity":null,"finish":null,"jockey":"佐々木志","carried_weight":52.0,"surface":"ダ","distance":"ダ1300","distance_m":1300,"track_condition":"不","time":"","margin":"","corners":"","pace":"","last_3f":null,"body_weight":"","winner_or_runner_up":"","prize":null,"data":{"body_weight":"","bracket":3,"carried_weight":52.0,"corners":"","distance":"ダ1300","distance_m":1300,"field_size":10,"finish":null,"horse_id":311,"horse_name":"オウケンミッキー","horse_number":3,"jockey":"佐々木志","last_3f":null,"margin":"","meeting":"水沢","netkeiba_id":"2019103828","odds":null,"pace":"","popularity":null,"prize":null,"race_date":"2023/11/27","race_id":"202336112705","race_name":"C2四組","race_no":5,"race_url":"https://db.netkeiba.com/race/202336112705/","raw":["2023/11/27","水沢","曇","5","C2四組","","10","3","3","","","取","佐々木志","52","ダ1300","","不","**","","","**","","","","","","","","計不","","","キセキノホシ",""],"source":"netkeiba","surface":"ダ","time":"","track_condition":"不","weather":"曇","winner_or_runner_up":""}},{"source":"netkeiba","race_date":"2023/11/06","meeting":"盛岡","weather":"曇","race_no":3,"race_name":"C2","race_id":"202335110603","race_url":"https://db.netkeiba.com/race/202335110603/","field_size":11,"bracket":3,"horse_number":3,"odds":234.8,"popularity":11,"finish":8,"jockey":"菅原辰徳","carried_weight":54.0,"surface":"ダ","distance":"ダ1000","distance_m":1000,"track_condition":"稍","time":"1:01.9","margin":"2.5","corners":"","pace":"","last_3f":null,"body_weight":"","winner_or_runner_up":"36.6","prize":null,"data":{"body_weight":"","bracket":3,"carried_weight":54.0,"corners":"","distance":"ダ1000","distance_m":1000,"field_size":11,"finish":8,"horse_id":311,"horse_name":"オウケンミッキー","horse_number":3,"jockey":"菅原辰徳","last_3f":null,"margin":"2.5","meeting":"盛岡","netkeiba_id":"2019103828","odds":234.8,"pace":"","popularity":11,"prize":null,"race_date":"2023/11/06","race_id":"202335110603","race_name":"C2","race_no":3,"race_url":"https://db.netkeiba.com/race/202335110603/","raw":["2023/11/06","盛岡","曇","3","C2","","11","3","3","234.8","11","8","菅原辰徳","54","ダ1000","","稍","**","1:01.9","2.5","**","","","","","7-7","","36.6","453(-7)","","","ジェイエルバルカー",""],"source":"netkeiba","surface":"ダ","time":"1:01.9","track_condition":"稍","weather":"曇","winner_or_runner_up":"36.6"}},{"source":"netkeiba","race_date":"2023/10/30","meeting":"盛岡","weather":"晴","race_no":2,"race_name":"C2","race_id":"202335103002","race_url":"https://db.netkeiba.com/race/202335103002/","field_size":8,"bracket":3,"horse_number":3,"odds":170.3,"popularity":8,"finish":7,"jockey":"岩本怜","carried_weight":54.0,"surface":"ダ","distance":"ダ1000","distance_m":1000,"track_condition":"良","time":"1:02.5","margin":"2.1","corners":"","pace":"","last_3f":null,"body_weight":"","winner_or_runner_up":"36.8","prize":null,"data":{"body_weight":"","bracket":3,"carried_weight":54.0,"corners":"","distance":"ダ1000","distance_m":1000,"field_size":8,"finish":7,"horse_id":311,"horse_name":"オウケンミッキー","horse_number":3,"jockey":"岩本怜","last_3f":null,"margin":"2.1","meeting":"盛岡","netkeiba_id":"2019103828","odds":170.3,"pace":"","popularity":8,"prize":null,"race_date":"2023/10/30","race_id":"202335103002","race_name":"C2","race_no":2,"race_url":"https://db.netkeiba.com/race/202335103002/","raw":["2023/10/30","盛岡","晴","2","C2","","8","3","3","170.3","8","7","岩本怜","54","ダ1000","","良","**","1:02.5","2.1","**","","","","","8-8","","36.8","460(0)","","","イディオム",""],"source":"netkeiba","surface":"ダ","time":"1:02.5","track_condition":"良","weather":"晴","winner_or_runner_up":"36.8"}},{"source":"netkeiba","race_date":"2023/10/23","meeting":"盛岡","weather":"晴","race_no":3,"race_name":"C2","race_id":"202335102303","race_url":"https://db.netkeiba.com/race/202335102303/","field_size":12,"bracket":8,"horse_number":12,"odds":174.9,"popularity":12,"finish":10,"jockey":"高野誠毅","carried_weight":54.0,"surface":"ダ","distance":"ダ1000","distance_m":1000,"track_condition":"不","time":"1:02.1","margin":"1.8","corners":"","pace":"","last_3f":null,"body_weight":"","winner_or_runner_up":"36.5","prize":null,"data":{"body_weight":"","bracket":8,"carried_weight":54.0,"corners":"","distance":"ダ1000","distance_m":1000,"field_size":12,"finish":10,"horse_id":311,"horse_name":"オウケンミッキー","horse_number":12,"jockey":"高野誠毅","last_3f":null,"margin":"1.8","meeting":"盛岡","netkeiba_id":"2019103828","odds":174.9,"pace":"","popularity":12,"prize":null,"race_date":"2023/10/23","race_id":"202335102303","race_name":"C2","race_no":3,"race_url":"https://db.netkeiba.com/race/202335102303/","raw":["2023/10/23","盛岡","晴","3","C2","","12","8","12","174.9","12","10","高野誠毅","54","ダ1000","","不","**","1:02.1","1.8","**","","","","","12-11","","36.5","460(+5)","","","クールシラユリ",""],"source":"netkeiba","surface":"ダ","time":"1:02.1","track_condition":"不","weather":"晴","winner_or_runner_up":"36.5"}},{"source":"netkeiba","race_date":"2023/09/24","meeting":"盛岡","weather":"晴","race_no":5,"race_name":"C2六組","race_id":"202335092405","race_url":"https://db.netkeiba.com/race/202335092405/","field_size":9,"bracket":2,"horse_number":2,"odds":6.8,"popularity":3,"finish":6,"jockey":"岩本怜","carried_weight":54.0,"surface":"ダ","distance":"ダ1200","distance_m":1200,"track_condition":"稍","time":"1:16.9","margin":"1.9","corners":"","pace":"","last_3f":null,"body_weight":"","winner_or_runner_up":"39.2","prize":null,"data":{"body_weight":"","bracket":2,"carried_weight":54.0,"corners":"","distance":"ダ1200","distance_m":1200,"field_size":9,"finish":6,"horse_id":311,"horse_name":"オウケンミッキー","horse_number":2,"jockey":"岩本怜","last_3f":null,"margin":"1.9","meeting":"盛岡","netkeiba_id":"2019103828","odds":6.8,"pace":"","popularity":3,"prize":null,"race_date":"2023/09/24","race_id":"202335092405","race_name":"C2六組","race_no":5,"race_url":"https://db.netkeiba.com/race/202335092405/","raw":["2023/09/24","盛岡","晴","5","C2六組","","9","2","2","6.8","3","6","岩本怜","54","ダ1200","","稍","**","1:16.9","1.9","**","","","","","4-3","","39.2","455(-2)","","","コイビトサンタ",""],"source":"netkeiba","surface":"ダ","time":"1:16.9","track_condition":"稍","weather":"晴","winner_or_runner_up":"39.2"}},{"source":"netkeiba","race_date":"2023/09/11","meeting":"水沢","weather":"曇","race_no":5,"race_name":"C2六組","race_id":"202336091105","race_url":"https://db.netkeiba.com/race/202336091105/","field_size":8,"bracket":3,"horse_number":3,"odds":11.5,"popularity":5,"finish":5,"jockey":"木村暁","carried_weight":54.0,"surface":"ダ","distance":"ダ1400","distance_m":1400,"track_condition":"稍","time":"1:31.8","margin":"2.4","corners":"","pace":"","last_3f":null,"body_weight":"","winner_or_runner_up":"40.5","prize":null,"data":{"body_weight":"","bracket":3,"carried_weight":54.0,"corners":"","distance":"ダ1400","distance_m":1400,"field_size":8,"finish":5,"horse_id":311,"horse_name":"オウケンミッキー","horse_number":3,"jockey":"木村暁","last_3f":null,"margin":"2.4","meeting":"水沢","netkeiba_id":"2019103828","odds":11.5,"pace":"","popularity":5,"prize":null,"race_date":"2023/09/11","race_id":"202336091105","race_name":"C2六組","race_no":5,"race_url":"https://db.netkeiba.com/race/202336091105/","raw":["2023/09/11","水沢","曇","5","C2六組","","8","3","3","11.5","5","5","木村暁","54","ダ1400","","稍","**","1:31.8","2.4","**","","","","","5-5-5-6","","40.5","457(-4)","","","フミタツティンクル","2.5"],"source":"netkeiba","surface":"ダ","time":"1:31.8","track_condition":"稍","weather":"曇","winner_or_runner_up":"40.5"}},{"source":"netkeiba","race_date":"2023/08/22","meeting":"水沢","weather":"晴","race_no":3,"race_name":"C2一組","race_id":"202336082203","race_url":"https://db.netkeiba.com/race/202336082203/","field_size":9,"bracket":5,"horse_number":5,"odds":21.0,"popularity":6,"finish":9,"jockey":"村上忍","carried_weight":54.0,"surface":"ダ","distance":"ダ1400","distance_m":1400,"track_condition":"稍","time":"1:31.6","margin":"1.8","corners":"","pace":"","last_3f":null,"body_weight":"","winner_or_runner_up":"41.7","prize":null,"data":{"body_weight":"","bracket":5,"carried_weight":54.0,"corners":"","distance":"ダ1400","distance_m":1400,"field_size":9,"finish":9,"horse_id":311,"horse_name":"オウケンミッキー","horse_number":5,"jockey":"村上忍","last_3f":null,"margin":"1.8","meeting":"水沢","netkeiba_id":"2019103828","odds":21.0,"pace":"","popularity":6,"prize":null,"race_date":"2023/08/22","race_id":"202336082203","race_name":"C2一組","race_no":3,"race_url":"https://db.netkeiba.com/race/202336082203/","raw":["2023/08/22","水沢","晴","3","C2一組","","9","5","5","21.0","6","9","村上忍","54","ダ1400","","稍","**","1:31.6","1.8","**","","","","","5-5-8-8","","41.7","461(+4)","","","アスカダイヤモンド",""],"source":"netkeiba","surface":"ダ","time":"1:31.6","track_condition":"稍","weather":"晴","winner_or_runner_up":"41.7"}},{"source":"netkeiba","race_date":"2023/08/08","meeting":"盛岡","weather":"晴","race_no":4,"race_name":"C2一組","race_id":"202335080804","race_url":"https://db.netkeiba.com/race/202335080804/","field_size":6,"bracket":4,"horse_number":4,"odds":3.0,"popularity":2,"finish":3,"jockey":"村上忍","carried_weight":54.0,"surface":"ダ","distance":"ダ1400","distance_m":1400,"track_condition":"良","time":"1:28.4","margin":"1.6","corners":"","pace":"","last_3f":null,"body_weight":"","winner_or_runner_up":"39.3","prize":null,"data":{"body_weight":"","bracket":4,"carried_weight":54.0,"corners":"","distance":"ダ1400","distance_m":1400,"field_size":6,"finish":3,"horse_id":311,"horse_name":"オウケンミッキー","horse_number":4,"jockey":"村上忍","last_3f":null,"margin":"1.6","meeting":"盛岡","netkeiba_id":"2019103828","odds":3.0,"pace":"","popularity":2,"prize":null,"race_date":"2023/08/08","race_id":"202335080804","race_name":"C2一組","race_no":4,"race_url":"https://db.netkeiba.com/race/202335080804/","raw":["2023/08/08","盛岡","晴","4","C2一組","","6","4","4","3.0","2","3","村上忍","54","ダ1400","","良","**","1:28.4","1.6","**","","","","","3-4","","39.3","457(+2)","","","アルティマボス","7.0"],"source":"netkeiba","surface":"ダ","time":"1:28.4","track_condition":"良","weather":"晴","winner_or_runner_up":"39.3"}},{"source":"netkeiba","race_date":"2023/07/24","meeting":"盛岡","weather":"晴","race_no":5,"race_name":"C2四組","race_id":"202335072405","race_url":"https://db.netkeiba.com/race/202335072405/","field_size":8,"bracket":5,"horse_number":5,"odds":8.2,"popularity":5,"finish":1,"jockey":"村上忍","carried_weight":54.0,"surface":"ダ","distance":"ダ1200","distance_m":1200,"track_condition":"良","time":"1:14.2","margin":"-0.1","corners":"","pace":"","last_3f":null,"body_weight":"","winner_or_runner_up":"37.1","prize":null,"data":{"body_weight":"","bracket":5,"carried_weight":54.0,"corners":"","distance":"ダ1200","distance_m":1200,"field_size":8,"finish":1,"horse_id":311,"horse_name":"オウケンミッキー","horse_number":5,"jockey":"村上忍","last_3f":null,"margin":"-0.1","meeting":"盛岡","netkeiba_id":"2019103828","odds":8.2,"pace":"","popularity":5,"prize":null,"race_date":"2023/07/24","race_id":"202335072405","race_name":"C2四組","race_no":5,"race_url":"https://db.netkeiba.com/race/202335072405/","raw":["2023/07/24","盛岡","晴","5","C2四組","","8","5","5","8.2","5","1","村上忍","54","ダ1200","","良","**","1:14.2","-0.1","**","","","","","1-1","","37.1","455(-11)","","","(ナツノトビラ)","35.0"],"source":"netkeiba","surface":"ダ","time":"1:14.2","track_condition":"良","weather":"晴","winner_or_runner_up":"37.1"}},{"source":"netkeiba","race_date":"2023/06/29","meeting":"門別","weather":"晴","race_no":9,"race_name":"クチナシ特別(C1)","race_id":"202330062909","race_url":"https://db.netkeiba.com/race/202330062909/","field_size":11,"bracket":5,"horse_number":5,"odds":319.7,"popularity":10,"finish":11,"jockey":"坂下秀樹","carried_weight":54.0,"surface":"ダ","distance":"ダ1000","distance_m":1000,"track_condition":"稍","time":"1:04.0","margin":"2.5","corners":"","pace":"","last_3f":null,"body_weight":"","winner_or_runner_up":"38.7","prize":null,"data":{"body_weight":"","bracket":5,"carried_weight":54.0,"corners":"","distance":"ダ1000","distance_m":1000,"field_size":11,"finish":11,"horse_id":311,"horse_name":"オウケンミッキー","horse_number":5,"jockey":"坂下秀樹","last_3f":null,"margin":"2.5","meeting":"門別","netkeiba_id":"2019103828","odds":319.7,"pace":"","popularity":10,"prize":null,"race_date":"2023/06/29","race_id":"202330062909","race_name":"クチナシ特別(C1)","race_no":9,"race_url":"https://db.netkeiba.com/race/202330062909/","raw":["2023/06/29","門別","晴","9","クチナシ特別(C1)","","11","5","5","319.7","10","11","坂下秀樹","54","ダ1000","","稍","**","1:04.0","2.5","**","","","","","9-9","","38.7","466(+6)","","","ワイルドラヴ",""],"source":"netkeiba","surface":"ダ","time":"1:04.0","track_condition":"稍","weather":"晴","winner_or_runner_up":"38.7"}},{"source":"netkeiba","race_date":"2023/06/14","meeting":"門別","weather":"曇","race_no":11,"race_name":"キンレンカ特別(C1)","race_id":"202330061411","race_url":"https://db.netkeiba.com/race/202330061411/","field_size":12,"bracket":1,"horse_number":1,"odds":201.5,"popularity":12,"finish":11,"jockey":"阿岸潤一","carried_weight":51.0,"surface":"ダ","distance":"ダ1000","distance_m":1000,"track_condition":"稍","time":"1:03.0","margin":"2.1","corners":"","pace":"","last_3f":null,"body_weight":"","winner_or_runner_up":"37.0","prize":null,"data":{"body_weight":"","bracket":1,"carried_weight":51.0,"corners":"","distance":"ダ1000","distance_m":1000,"field_size":12,"finish":11,"horse_id":311,"horse_name":"オウケンミッキー","horse_number":1,"jockey":"阿岸潤一","last_3f":null,"margin":"2.1","meeting":"門別","netkeiba_id":"2019103828","odds":201.5,"pace":"","popularity":12,"prize":null,"race_date":"2023/06/14","race_id":"202330061411","race_name":"キンレンカ特別(C1)","race_no":11,"race_url":"https://db.netkeiba.com/race/202330061411/","raw":["2023/06/14","門別","曇","11","キンレンカ特別(C1)","","12","1","1","201.5","12","11","阿岸潤一","51","ダ1000","","稍","**","1:03.0","2.1","**","","","","","12-12","","37.0","460(0)","","","メイクザウインド",""],"source":"netkeiba","surface":"ダ","time":"1:03.0","track_condition":"稍","weather":"曇","winner_or_runner_up":"37.0"}},{"source":"netkeiba","race_date":"2023/05/30","meeting":"門別","weather":"晴","race_no":8,"race_name":"クレマチス特別(C1)","race_id":"202330053008","race_url":"https://db.netkeiba.com/race/202330053008/","field_size":12,"bracket":6,"horse_number":8,"odds":196.6,"popularity":9,"finish":11,"jockey":"坂下秀樹","carried_weight":54.0,"surface":"ダ","distance":"ダ1200","distance_m":1200,"track_condition":"良","time":"1:17.5","margin":"2.8","corners":"","pace":"","last_3f":null,"body_weight":"","winner_or_runner_up":"38.9","prize":null,"data":{"body_weight":"","bracket":6,"carried_weight":54.0,"corners":"","distance":"ダ1200","distance_m":1200,"field_size":12,"finish":11,"horse_id":311,"horse_name":"オウケンミッキー","horse_number":8,"jockey":"坂下秀樹","last_3f":null,"margin":"2.8","meeting":"門別","netkeiba_id":"2019103828","odds":196.6,"pace":"","popularity":9,"prize":null,"race_date":"2023/05/30","race_id":"202330053008","race_name":"クレマチス特別(C1)","race_no":8,"race_url":"https://db.netkeiba.com/race/202330053008/","raw":["2023/05/30","門別","晴","8","クレマチス特別(C1)","","12","6","8","196.6","9","11","坂下秀樹","54","ダ1200","","良","**","1:17.5","2.8","**","","","","","11-11","","38.9","460(+2)","","","ブリックロード",""],"source":"netkeiba","surface":"ダ","time":"1:17.5","track_condition":"良","weather":"晴","winner_or_runner_up":"38.9"}},{"source":"netkeiba","race_date":"2023/05/17","meeting":"門別","weather":"晴","race_no":7,"race_name":"ウツギ特別(C1)","race_id":"202330051707","race_url":"https://db.netkeiba.com/race/202330051707/","field_size":8,"bracket":1,"horse_number":1,"odds":147.4,"popularity":8,"finish":6,"jockey":"宮平鷹志","carried_weight":54.0,"surface":"ダ","distance":"ダ1000","distance_m":1000,"track_condition":"良","time":"1:02.6","margin":"1.1","corners":"","pace":"","last_3f":null,"body_weight":"","winner_or_runner_up":"36.3","prize":null,"data":{"body_weight":"","bracket":1,"carried_weight":54.0,"corners":"","distance":"ダ1000","distance_m":1000,"field_size":8,"finish":6,"horse_id":311,"horse_name":"オウケンミッキー","horse_number":1,"jockey":"宮平鷹志","last_3f":null,"margin":"1.1","meeting":"門別","netkeiba_id":"2019103828","odds":147.4,"pace":"","popularity":8,"prize":null,"race_date":"2023/05/17","race_id":"202330051707","race_name":"ウツギ特別(C1)","race_no":7,"race_url":"https://db.netkeiba.com/race/202330051707/","raw":["2023/05/17","門別","晴","7","ウツギ特別(C1)","","8","1","1","147.4","8","6","宮平鷹志","54","ダ1000","","良","**","1:02.6","1.1","**","","","","","8-8","","36.3","458(+6)","","","ラブリプリンチャン",""],"source":"netkeiba","surface":"ダ","time":"1:02.6","track_condition":"良","weather":"晴","winner_or_runner_up":"36.3"}},{"source":"netkeiba","race_date":"2023/05/03","meeting":"門別","weather":"晴","race_no":9,"race_name":"来て見て恋してピンク(C2)","race_id":"202330050309","race_url":"https://db.netkeiba.com/race/202330050309/","field_size":10,"bracket":1,"horse_number":1,"odds":49.4,"popularity":8,"finish":7,"jockey":"宮平鷹志","carried_weight":54.0,"surface":"ダ","distance":"ダ1000","distance_m":1000,"track_condition":"良","time":"1:03.4","margin":"1.6","corners":"","pace":"","last_3f":null,"body_weight":"","winner_or_runner_up":"37.6","prize":null,"data":{"body_weight":"","bracket":1,"carried_weight":54.0,"corners":"","distance":"ダ1000","distance_m":1000,"field_size":10,"finish":7,"horse_id":311,"horse_name":"オウケンミッキー","horse_number":1,"jockey":"宮平鷹志","last_3f":null,"margin":"1.6","meeting":"門別","netkeiba_id":"2019103828","odds":49.4,"pace":"","popularity":8,"prize":null,"race_date":"2023/05/03","race_id":"202330050309","race_name":"来て見て恋してピンク(C2)","race_no":9,"race_url":"https://db.netkeiba.com/race/202330050309/","raw":["2023/05/03","門別","晴","9","来て見て恋してピンク(C2)","","10","1","1","49.4","8","7","宮平鷹志","54","ダ1000","","良","**","1:03.4","1.6","**","","","","","9-8","","37.6","452(-8)","","","コインポケット",""],"source":"netkeiba","surface":"ダ","time":"1:03.4","track_condition":"良","weather":"晴","winner_or_runner_up":"37.6"}},{"source":"netkeiba","race_date":"2023/04/26","meeting":"門別","weather":"曇","race_no":8,"race_name":"3歳以上C1ー2C2","race_id":"202330042608","race_url":"https://db.netkeiba.com/race/202330042608/","field_size":7,"bracket":3,"horse_number":3,"odds":27.6,"popularity":6,"finish":6,"jockey":"坂下秀樹","carried_weight":54.0,"surface":"ダ","distance":"ダ1200","distance_m":1200,"track_condition":"不","time":"1:15.0","margin":"1.6","corners":"","pace":"","last_3f":null,"body_weight":"","winner_or_runner_up":"38.2","prize":null,"data":{"body_weight":"","bracket":3,"carried_weight":54.0,"corners":"","distance":"ダ1200","distance_m":1200,"field_size":7,"finish":6,"horse_id":311,"horse_name":"オウケンミッキー","horse_number":3,"jockey":"坂下秀樹","last_3f":null,"margin":"1.6","meeting":"門別","netkeiba_id":"2019103828","odds":27.6,"pace":"","popularity":6,"prize":null,"race_date":"2023/04/26","race_id":"202330042608","race_name":"3歳以上C1ー2C2","race_no":8,"race_url":"https://db.netkeiba.com/race/202330042608/","raw":["2023/04/26","門別","曇","8","3歳以上C1ー2C2","","7","3","3","27.6","6","6","坂下秀樹","54","ダ1200","","不","**","1:15.0","1.6","**","","","","","3-3","","38.2","460(-6)","","","タンバオー",""],"source":"netkeiba","surface":"ダ","time":"1:15.0","track_condition":"不","weather":"曇","winner_or_runner_up":"38.2"}},{"source":"netkeiba","race_date":"2023/04/11","meeting":"水沢","weather":"晴","race_no":11,"race_name":"C1一組","race_id":"202336041111","race_url":"https://db.netkeiba.com/race/202336041111/","field_size":12,"bracket":1,"horse_number":1,"odds":94.7,"popularity":9,"finish":11,"jockey":"岩本怜","carried_weight":54.0,"surface":"ダ","distance":"ダ1600","distance_m":1600,"track_condition":"良","time":"1:46.9","margin":"2.9","corners":"","pace":"","last_3f":null,"body_weight":"","winner_or_runner_up":"41.3","prize":null,"data":{"body_weight":"","bracket":1,"carried_weight":54.0,"corners":"","distance":"ダ1600","distance_m":1600,"field_size":12,"finish":11,"horse_id":311,"horse_name":"オウケンミッキー","horse_number":1,"jockey":"岩本怜","last_3f":null,"margin":"2.9","meeting":"水沢","netkeiba_id":"2019103828","odds":94.7,"pace":"","popularity":9,"prize":null,"race_date":"2023/04/11","race_id":"202336041111","race_name":"C1一組","race_no":11,"race_url":"https://db.netkeiba.com/race/202336041111/","raw":["2023/04/11","水沢","晴","11","C1一組","","12","1","1","94.7","9","11","岩本怜","54","ダ1600","","良","**","1:46.9","2.9","**","","","","","6-5-10-11","","41.3","466(+15)","","","ローガン",""],"source":"netkeiba","surface":"ダ","time":"1:46.9","track_condition":"良","weather":"晴","winner_or_runner_up":"41.3"}},{"source":"netkeiba","race_date":"2023/03/19","meeting":"水沢","weather":"晴","race_no":6,"race_name":"B2","race_id":"202336031906","race_url":"https://db.netkeiba.com/race/202336031906/","field_size":9,"bracket":2,"horse_number":2,"odds":19.3,"popularity":5,"finish":7,"jockey":"岩本怜","carried_weight":54.0,"surface":"ダ","distance":"ダ1300","distance_m":1300,"track_condition":"良","time":"1:26.1","margin":"1.9","corners":"","pace":"","last_3f":null,"body_weight":"","winner_or_runner_up":"40.5","prize":null,"data":{"body_weight":"","bracket":2,"carried_weight":54.0,"corners":"","distance":"ダ1300","distance_m":1300,"field_size":9,"finish":7,"horse_id":311,"horse_name":"オウケンミッキー","horse_number":2,"jockey":"岩本怜","last_3f":null,"margin":"1.9","meeting":"水沢","netkeiba_id":"2019103828","odds":19.3,"pace":"","popularity":5,"prize":null,"race_date":"2023/03/19","race_id":"202336031906","race_name":"B2","race_no":6,"race_url":"https://db.netkeiba.com/race/202336031906/","raw":["2023/03/19","水沢","晴","6","B2","","9","2","2","19.3","5","7","岩本怜","54","ダ1300","","良","**","1:26.1","1.9","**","","","","","9-8-8-8","","40.5","451(-3)","","","アブソルートピッチ",""],"source":"netkeiba","surface":"ダ","time":"1:26.1","track_condition":"良","weather":"晴","winner_or_runner_up":"40.5"}},{"source":"netkeiba","race_date":"2023/03/11","meeting":"水沢","weather":"晴","race_no":6,"race_name":"B2","race_id":"202336031106","race_url":"https://db.netkeiba.com/race/202336031106/","field_size":12,"bracket":6,"horse_number":8,"odds":2.3,"popularity":1,"finish":7,"jockey":"岩本怜","carried_weight":54.0,"surface":"ダ","distance":"ダ1400","distance_m":1400,"track_condition":"良","time":"1:32.6","margin":"1.4","corners":"","pace":"","last_3f":null,"body_weight":"","winner_or_runner_up":"42.6","prize":null,"data":{"body_weight":"","bracket":6,"carried_weight":54.0,"corners":"","distance":"ダ1400","distance_m":1400,"field_size":12,"finish":7,"horse_id":311,"horse_name":"オウケンミッキー","horse_number":8,"jockey":"岩本怜","last_3f":null,"margin":"1.4","meeting":"水沢","netkeiba_id":"2019103828","odds":2.3,"pace":"","popularity":1,"prize":null,"race_date":"2023/03/11","race_id":"202336031106","race_name":"B2","race_no":6,"race_url":"https://db.netkeiba.com/race/202336031106/","raw":["2023/03/11","水沢","晴","6","B2","","12","6","8","2.3","1","7","岩本怜","54","ダ1400","","良","**","1:32.6","1.4","**","","","","","2-2-2-5","","42.6","454(+6)","","","トーアクリスティー",""],"source":"netkeiba","surface":"ダ","time":"1:32.6","track_condition":"良","weather":"晴","winner_or_runner_up":"42.6"}},{"source":"netkeiba","race_date":"2023/02/03","meeting":"川崎","weather":"曇","race_no":9,"race_name":"C1一　二三(C1二)","race_id":"202345020309","race_url":"https://db.netkeiba.com/race/202345020309/","field_size":11,"bracket":3,"horse_number":3,"odds":181.3,"popularity":11,"finish":10,"jockey":"櫻井光輔","carried_weight":54.0,"surface":"ダ","distance":"ダ1400","distance_m":1400,"track_condition":"良","time":"1:35.0","margin":"2.2","corners":"","pace":"","last_3f":null,"body_weight":"","winner_or_runner_up":"43.0","prize":null,"data":{"body_weight":"","bracket":3,"carried_weight":54.0,"corners":"","distance":"ダ1400","distance_m":1400,"field_size":11,"finish":10,"horse_id":311,"horse_name":"オウケンミッキー","horse_number":3,"jockey":"櫻井光輔","last_3f":null,"margin":"2.2","meeting":"川崎","netkeiba_id":"2019103828","odds":181.3,"pace":"","popularity":11,"prize":null,"race_date":"2023/02/03","race_id":"202345020309","race_name":"C1一　二三(C1二)","race_no":9,"race_url":"https://db.netkeiba.com/race/202345020309/","raw":["2023/02/03","川崎","曇","9","C1一 二三(C1二)","","11","3","3","181.3","11","10","櫻井光輔","54","ダ1400","","良","**","1:35.0","2.2","**","","","","","6-6-10-10","37.6-43.0","43.0","448(-2)","","","スティールタイム",""],"source":"netkeiba","surface":"ダ","time":"1:35.0","track_condition":"良","weather":"曇","winner_or_runner_up":"43.0"}},{"source":"netkeiba","race_date":"2023/01/20","meeting":"船橋","weather":"晴","race_no":12,"race_name":"初富賞(C1)","race_id":"202343012012","race_url":"https://db.netkeiba.com/race/202343012012/","field_size":14,"bracket":7,"horse_number":12,"odds":337.3,"popularity":13,"finish":7,"jockey":"中越琉世","carried_weight":54.0,"surface":"ダ","distance":"ダ1600","distance_m":1600,"track_condition":"良","time":"1:48.0","margin":"1.6","corners":"","pace":"","last_3f":null,"body_weight":"","winner_or_runner_up":"42.0","prize":null,"data":{"body_weight":"","bracket":7,"carried_weight":54.0,"corners":"","distance":"ダ1600","distance_m":1600,"field_size":14,"finish":7,"horse_id":311,"horse_name":"オウケンミッキー","horse_number":12,"jockey":"中越琉世","last_3f":null,"margin":"1.6","meeting":"船橋","netkeiba_id":"2019103828","odds":337.3,"pace":"","popularity":13,"prize":null,"race_date":"2023/01/20","race_id":"202343012012","race_name":"初富賞(C1)","race_no":12,"race_url":"https://db.netkeiba.com/race/202343012012/","raw":["2023/01/20","船橋","晴","12","初富賞(C1)","","14","7","12","337.3","13","7","中越琉世","54","ダ1600","","良","**","1:48.0","1.6","**","","","","","4-4-6-8","39.3-41.1","42.0","450(-3)","","","インペラートル",""],"source":"netkeiba","surface":"ダ","time":"1:48.0","track_condition":"良","weather":"晴","winner_or_runner_up":"42.0"}},{"source":"netkeiba","race_date":"2023/01/04","meeting":"川崎","weather":"晴","race_no":8,"race_name":"C1一　二三(C1二)","race_id":"202345010408","race_url":"https://db.netkeiba.com/race/202345010408/","field_size":10,"bracket":7,"horse_number":7,"odds":39.0,"popularity":8,"finish":10,"jockey":"今野忠成","carried_weight":54.0,"surface":"ダ","distance":"ダ1400","distance_m":1400,"track_condition":"良","time":"1:35.8","margin":"4.8","corners":"","pace":"","last_3f":null,"body_weight":"","winner_or_runner_up":"44.1","prize":null,"data":{"body_weight":"","bracket":7,"carried_weight":54.0,"corners":"","distance":"ダ1400","distance_m":1400,"field_size":10,"finish":10,"horse_id":311,"horse_name":"オウケンミッキー","horse_number":7,"jockey":"今野忠成","last_3f":null,"margin":"4.8","meeting":"川崎","netkeiba_id":"2019103828","odds":39.0,"pace":"","popularity":8,"prize":null,"race_date":"2023/01/04","race_id":"202345010408","race_name":"C1一　二三(C1二)","race_no":8,"race_url":"https://db.netkeiba.com/race/202345010408/","raw":["2023/01/04","川崎","晴","8","C1一 二三(C1二)","","10","7","7","39.0","8","10","今野忠成","54","ダ1400","","良","**","1:35.8","4.8","**","","","","","4-3-5-8","39.3-39.7","44.1","453(+1)","","","モンディアマン",""],"source":"netkeiba","surface":"ダ","time":"1:35.8","track_condition":"良","weather":"晴","winner_or_runner_up":"44.1"}},{"source":"netkeiba","race_date":"2022/12/13","meeting":"川崎","weather":"晴","race_no":9,"race_name":"大磯港みなとオアシス(C1五)","race_id":"202245121309","race_url":"https://db.netkeiba.com/race/202245121309/","field_size":9,"bracket":8,"horse_number":9,"odds":48.2,"popularity":5,"finish":2,"jockey":"中越琉世","carried_weight":54.0,"surface":"ダ","distance":"ダ1400","distance_m":1400,"track_condition":"重","time":"1:33.2","margin":"0.6","corners":"","pace":"","last_3f":null,"body_weight":"","winner_or_runner_up":"40.4","prize":null,"data":{"body_weight":"","bracket":8,"carried_weight":54.0,"corners":"","distance":"ダ1400","distance_m":1400,"field_size":9,"finish":2,"horse_id":311,"horse_name":"オウケンミッキー","horse_number":9,"jockey":"中越琉世","last_3f":null,"margin":"0.6","meeting":"川崎","netkeiba_id":"2019103828","odds":48.2,"pace":"","popularity":5,"prize":null,"race_date":"2022/12/13","race_id":"202245121309","race_name":"大磯港みなとオアシス(C1五)","race_no":9,"race_url":"https://db.netkeiba.com/race/202245121309/","raw":["2022/12/13","川崎","晴","9","大磯港みなとオアシス(C1五)","","9","8","9","48.2","5","2","中越琉世","54","ダ1400","","重","**","1:33.2","0.6","**","","","","","4-4-1-2","40.3-39.9","40.4","452(-3)","","","モンディアマン","48.0"],"source":"netkeiba","surface":"ダ","time":"1:33.2","track_condition":"重","weather":"晴","winner_or_runner_up":"40.4"}},{"source":"netkeiba","race_date":"2022/12/01","meeting":"船橋","weather":"曇","race_no":8,"race_name":"アンスリウム2200(C1)","race_id":"202243120108","race_url":"https://db.netkeiba.com/race/202243120108/","field_size":10,"bracket":3,"horse_number":3,"odds":27.9,"popularity":9,"finish":8,"jockey":"野畑凌","carried_weight":52.0,"surface":"ダ","distance":"ダ2200","distance_m":2200,"track_condition":"良","time":"2:36.1","margin":"3.0","corners":"","pace":"","last_3f":null,"body_weight":"","winner_or_runner_up":"46.0","prize":null,"data":{"body_weight":"","bracket":3,"carried_weight":52.0,"corners":"","distance":"ダ2200","distance_m":2200,"field_size":10,"finish":8,"horse_id":311,"horse_name":"オウケンミッキー","horse_number":3,"jockey":"野畑凌","last_3f":null,"margin":"3.0","meeting":"船橋","netkeiba_id":"2019103828","odds":27.9,"pace":"","popularity":9,"prize":null,"race_date":"2022/12/01","race_id":"202243120108","race_name":"アンスリウム2200(C1)","race_no":8,"race_url":"https://db.netkeiba.com/race/202243120108/","raw":["2022/12/01","船橋","曇","8","アンスリウム2200(C1)","","10","3","3","27.9","9","8","野畑凌","52","ダ2200","","良","**","2:36.1","3.0","**","","","","","1-1-1-1","39.9-43.0","46.0","455(-6)","","","ドラム",""],"source":"netkeiba","surface":"ダ","time":"2:36.1","track_condition":"良","weather":"曇","winner_or_runner_up":"46.0"}},{"source":"netkeiba","race_date":"2022/11/09","meeting":"川崎","weather":"晴","race_no":6,"race_name":"C1四　五六(C1五)","race_id":"202245110906","race_url":"https://db.netkeiba.com/race/202245110906/","field_size":12,"bracket":6,"horse_number":8,"odds":5.8,"popularity":3,"finish":12,"jockey":"野畑凌","carried_weight":52.0,"surface":"ダ","distance":"ダ1400","distance_m":1400,"track_condition":"良","time":"1:35.2","margin":"3.0","corners":"","pace":"","last_3f":null,"body_weight":"","winner_or_runner_up":"42.9","prize":null,"data":{"body_weight":"","bracket":6,"carried_weight":52.0,"corners":"","distance":"ダ1400","distance_m":1400,"field_size":12,"finish":12,"horse_id":311,"horse_name":"オウケンミッキー","horse_number":8,"jockey":"野畑凌","last_3f":null,"margin":"3.0","meeting":"川崎","netkeiba_id":"2019103828","odds":5.8,"pace":"","popularity":3,"prize":null,"race_date":"2022/11/09","race_id":"202245110906","race_name":"C1四　五六(C1五)","race_no":6,"race_url":"https://db.netkeiba.com/race/202245110906/","raw":["2022/11/09","川崎","晴","6","C1四 五六(C1五)","","12","6","8","5.8","3","12","野畑凌","52","ダ1400","","良","**","1:35.2","3.0","**","","","","","6-7-5-11","39.0-40.5","42.9","461(+15)","","","ソルティエラ",""],"source":"netkeiba","surface":"ダ","time":"1:35.2","track_condition":"良","weather":"晴","winner_or_runner_up":"42.9"}},{"source":"netkeiba","race_date":"2022/09/03","meeting":"4小倉7","weather":"曇","race_no":8,"race_name":"3歳以上1勝クラス","race_id":"202210040708","race_url":"https://db.netkeiba.com/race/202210040708/","field_size":15,"bracket":2,"horse_number":2,"odds":100.0,"popularity":14,"finish":13,"jockey":"国分優作","carried_weight":53.0,"surface":"芝","distance":"芝1200","distance_m":1200,"track_condition":"重","time":"1:09.8","margin":"1.0","corners":"","pace":"","last_3f":null,"body_weight":"","winner_or_runner_up":"34.9","prize":null,"data":{"body_weight":"","bracket":2,"carried_weight":53.0,"corners":"","distance":"芝1200","distance_m":1200,"field_size":15,"finish":13,"horse_id":311,"horse_name":"オウケンミッキー","horse_number":2,"jockey":"国分優作","last_3f":null,"margin":"1.0","meeting":"4小倉7","netkeiba_id":"2019103828","odds":100.0,"pace":"","popularity":14,"prize":null,"race_date":"2022/09/03","race_id":"202210040708","race_name":"3歳以上1勝クラス","race_no":8,"race_url":"https://db.netkeiba.com/race/202210040708/","raw":["2022/09/03","4小倉7","曇","8","3歳以上1勝クラス","","15","2","2","100.0","14","13","国分優作","53","芝1200","","重","**","1:09.8","1.0","**","","","","","9-11","34.0-34.8","34.9","446(0)","","","クァンタムレルム",""],"source":"netkeiba","surface":"芝","time":"1:09.8","track_condition":"重","weather":"曇","winner_or_runner_up":"34.9"}},{"source":"netkeiba","race_date":"2022/08/27","meeting":"4小倉5","weather":"晴","race_no":6,"race_name":"3歳未勝利","race_id":"202210040506","race_url":"https://db.netkeiba.com/race/202210040506/","field_size":17,"bracket":6,"horse_number":12,"odds":26.5,"popularity":7,"finish":7,"jockey":"角田大河","carried_weight":51.0,"surface":"芝","distance":"芝1200","distance_m":1200,"track_condition":"良","time":"1:09.0","margin":"0.6","corners":"","pace":"","last_3f":null,"body_weight":"","winner_or_runner_up":"35.0","prize":null,"data":{"body_weight":"","bracket":6,"carried_weight":51.0,"corners":"","distance":"芝1200","distance_m":1200,"field_size":17,"finish":7,"horse_id":311,"horse_name":"オウケンミッキー","horse_number":12,"jockey":"角田大河","last_3f":null,"margin":"0.6","meeting":"4小倉5","netkeiba_id":"2019103828","odds":26.5,"pace":"","popularity":7,"prize":null,"race_date":"2022/08/27","race_id":"202210040506","race_name":"3歳未勝利","race_no":6,"race_url":"https://db.netkeiba.com/race/202210040506/","raw":["2022/08/27","4小倉5","晴","6","3歳未勝利","","17","6","12","26.5","7","7","角田大河","51","芝1200","","良","**","1:09.0","0.6","**","","","","","3-4","33.8-34.6","35.0","446(+2)","","","アドマイヤラヴィ",""],"source":"netkeiba","surface":"芝","time":"1:09.0","track_condition":"良","weather":"晴","winner_or_runner_up":"35.0"}},{"source":"netkeiba","race_date":"2022/06/25","meeting":"3阪神3","weather":"晴","race_no":2,"race_name":"3歳未勝利","race_id":"202209030302","race_url":"https://db.netkeiba.com/race/202209030302/","field_size":16,"bracket":6,"horse_number":11,"odds":14.3,"popularity":7,"finish":10,"jockey":"岩田望来","carried_weight":54.0,"surface":"ダ","distance":"ダ1200","distance_m":1200,"track_condition":"良","time":"1:14.4","margin":"1.9","corners":"","pace":"","last_3f":null,"body_weight":"","winner_or_runner_up":"38.7","prize":null,"data":{"body_weight":"","bracket":6,"carried_weight":54.0,"corners":"","distance":"ダ1200","distance_m":1200,"field_size":16,"finish":10,"horse_id":311,"horse_name":"オウケンミッキー","horse_number":11,"jockey":"岩田望来","last_3f":null,"margin":"1.9","meeting":"3阪神3","netkeiba_id":"2019103828","odds":14.3,"pace":"","popularity":7,"prize":null,"race_date":"2022/06/25","race_id":"202209030302","race_name":"3歳未勝利","race_no":2,"race_url":"https://db.netkeiba.com/race/202209030302/","raw":["2022/06/25","3阪神3","晴","2","3歳未勝利","","16","6","11","14.3","7","10","岩田望来","54","ダ1200","","良","**","1:14.4","1.9","**","","","","","8-10","34.6-37.9","38.7","444(+6)","","","ニホンピロクリーク",""],"source":"netkeiba","surface":"ダ","time":"1:14.4","track_condition":"良","weather":"晴","winner_or_runner_up":"38.7"}},{"source":"netkeiba","race_date":"2022/05/28","meeting":"3中京7","weather":"晴","race_no":2,"race_name":"3歳未勝利","race_id":"202207030702","race_url":"https://db.netkeiba.com/race/202207030702/","field_size":16,"bracket":4,"horse_number":7,"odds":21.1,"popularity":6,"finish":2,"jockey":"小崎綾也","carried_weight":54.0,"surface":"ダ","distance":"ダ1200","distance_m":1200,"track_condition":"重","time":"1:13.1","margin":"0.2","corners":"","pace":"","last_3f":null,"body_weight":"","winner_or_runner_up":"38.0","prize":null,"data":{"body_weight":"","bracket":4,"carried_weight":54.0,"corners":"","distance":"ダ1200","distance_m":1200,"field_size":16,"finish":2,"horse_id":311,"horse_name":"オウケンミッキー","horse_number":7,"jockey":"小崎綾也","last_3f":null,"margin":"0.2","meeting":"3中京7","netkeiba_id":"2019103828","odds":21.1,"pace":"","popularity":6,"prize":null,"race_date":"2022/05/28","race_id":"202207030702","race_name":"3歳未勝利","race_no":2,"race_url":"https://db.netkeiba.com/race/202207030702/","raw":["2022/05/28","3中京7","晴","2","3歳未勝利","","16","4","7","21.1","6","2","小崎綾也","54","ダ1200","","重","**","1:13.1","0.2","**","","","","","4-4","34.7-38.2","38.0","438(-2)","","","ビリーズバウンス","210.0"],"source":"netkeiba","surface":"ダ","time":"1:13.1","track_condition":"重","weather":"晴","winner_or_runner_up":"38.0"}},{"source":"netkeiba","race_date":"2022/05/15","meeting":"1新潟4","weather":"晴","race_no":2,"race_name":"3歳未勝利","race_id":"202204010402","race_url":"https://db.netkeiba.com/race/202204010402/","field_size":16,"bracket":6,"horse_number":12,"odds":15.9,"popularity":7,"finish":8,"jockey":"横山琉人","carried_weight":51.0,"surface":"芝","distance":"芝1200","distance_m":1200,"track_condition":"良","time":"1:11.0","margin":"1.2","corners":"","pace":"","last_3f":null,"body_weight":"","winner_or_runner_up":"35.9","prize":null,"data":{"body_weight":"","bracket":6,"carried_weight":51.0,"corners":"","distance":"芝1200","distance_m":1200,"field_size":16,"finish":8,"horse_id":311,"horse_name":"オウケンミッキー","horse_number":12,"jockey":"横山琉人","last_3f":null,"margin":"1.2","meeting":"1新潟4","netkeiba_id":"2019103828","odds":15.9,"pace":"","popularity":7,"prize":null,"race_date":"2022/05/15","race_id":"202204010402","race_name":"3歳未勝利","race_no":2,"race_url":"https://db.netkeiba.com/race/202204010402/","raw":["2022/05/15","1新潟4","晴","2","3歳未勝利","","16","6","12","15.9","7","8","横山琉人","51","芝1200","","良","**","1:11.0","1.2","**","","","","","10-10","34.1-35.7","35.9","440(-10)","","","グランアリエル",""],"source":"netkeiba","surface":"芝","time":"1:11.0","track_condition":"良","weather":"晴","winner_or_runner_up":"35.9"}},{"source":"netkeiba","race_date":"2022/02/19","meeting":"2小倉3","weather":"雨","race_no":2,"race_name":"3歳未勝利","race_id":"202210020302","race_url":"https://db.netkeiba.com/race/202210020302/","field_size":18,"bracket":7,"horse_number":13,"odds":53.6,"popularity":12,"finish":3,"jockey":"小崎綾也","carried_weight":54.0,"surface":"芝","distance":"芝1200","distance_m":1200,"track_condition":"稍","time":"1:10.6","margin":"0.1","corners":"","pace":"","last_3f":null,"body_weight":"","winner_or_runner_up":"35.7","prize":null,"data":{"body_weight":"","bracket":7,"carried_weight":54.0,"corners":"","distance":"芝1200","distance_m":1200,"field_size":18,"finish":3,"horse_id":311,"horse_name":"オウケンミッキー","horse_number":13,"jockey":"小崎綾也","last_3f":null,"margin":"0.1","meeting":"2小倉3","netkeiba_id":"2019103828","odds":53.6,"pace":"","popularity":12,"prize":null,"race_date":"2022/02/19","race_id":"202210020302","race_name":"3歳未勝利","race_no":2,"race_url":"https://db.netkeiba.com/race/202210020302/","raw":["2022/02/19","2小倉3","雨","2","3歳未勝利","","18","7","13","53.6","12","3","小崎綾也","54","芝1200","","稍","**","1:10.6","0.1","**","","","","","2-2","34.6-35.9","35.7","450(-4)","","","ニホンピロポート","130.0"],"source":"netkeiba","surface":"芝","time":"1:10.6","track_condition":"稍","weather":"雨","winner_or_runner_up":"35.7"}},{"source":"netkeiba","race_date":"2021/11/13","meeting":"2福島3","weather":"晴","race_no":3,"race_name":"2歳未勝利","race_id":"202103020303","race_url":"https://db.netkeiba.com/race/202103020303/","field_size":16,"bracket":2,"horse_number":3,"odds":5.9,"popularity":3,"finish":16,"jockey":"小沢大仁","carried_weight":51.0,"surface":"芝","distance":"芝1200","distance_m":1200,"track_condition":"良","time":"1:13.3","margin":"2.9","corners":"","pace":"","last_3f":null,"body_weight":"","winner_or_runner_up":"37.7","prize":null,"data":{"body_weight":"","bracket":2,"carried_weight":51.0,"corners":"","distance":"芝1200","distance_m":1200,"field_size":16,"finish":16,"horse_id":311,"horse_name":"オウケンミッキー","horse_number":3,"jockey":"小沢大仁","last_3f":null,"margin":"2.9","meeting":"2福島3","netkeiba_id":"2019103828","odds":5.9,"pace":"","popularity":3,"prize":null,"race_date":"2021/11/13","race_id":"202103020303","race_name":"2歳未勝利","race_no":3,"race_url":"https://db.netkeiba.com/race/202103020303/","raw":["2021/11/13","2福島3","晴","3","2歳未勝利","","16","2","3","5.9","3","16","小沢大仁","51","芝1200","","良","**","1:13.3","2.9","**","","","","","12-12","34.5-35.9","37.7","454(-8)","","","バーニングアイズ",""],"source":"netkeiba","surface":"芝","time":"1:13.3","track_condition":"良","weather":"晴","winner_or_runner_up":"37.7"}},{"source":"netkeiba","race_date":"2021/10/23","meeting":"4阪神5","weather":"晴","race_no":5,"race_name":"2歳新馬","race_id":"202109040505","race_url":"https://db.netkeiba.com/race/202109040505/","field_size":12,"bracket":5,"horse_number":5,"odds":6.1,"popularity":3,"finish":3,"jockey":"岩田望来","carried_weight":54.0,"surface":"芝","distance":"芝1200","distance_m":1200,"track_condition":"良","time":"1:10.7","margin":"0.6","corners":"","pace":"","last_3f":null,"body_weight":"","winner_or_runner_up":"35.3","prize":null,"data":{"body_weight":"","bracket":5,"carried_weight":54.0,"corners":"","distance":"芝1200","distance_m":1200,"field_size":12,"finish":3,"horse_id":311,"horse_name":"オウケンミッキー","horse_number":5,"jockey":"岩田望来","last_3f":null,"margin":"0.6","meeting":"4阪神5","netkeiba_id":"2019103828","odds":6.1,"pace":"","popularity":3,"prize":null,"race_date":"2021/10/23","race_id":"202109040505","race_name":"2歳新馬","race_no":5,"race_url":"https://db.netkeiba.com/race/202109040505/","raw":["2021/10/23","4阪神5","晴","5","2歳新馬","","12","5","5","6.1","3","3","岩田望来","54","芝1200","","良","**","1:10.7","0.6","**","","","","","3-6","34.8-35.3","35.3","462(0)","","","ナムラデイリリー","180.0"],"source":"netkeiba","surface":"芝","time":"1:10.7","track_condition":"良","weather":"晴","winner_or_runner_up":"35.3"}}],"stud":[]}