{"horse":{"id":348,"name":"ショウナンマントル","sex":"セン","birth_year":2021,"birth_date":"2021年1月10日","color":"鹿毛","status":"セ5歳","sire":"ドゥラメンテ","dam":"セシリア","broodmare_sire":"アグネスタキオン","bms_line":"Sunday Silence","female_family":"F2-f","imported_foundation_mare":"マシュール(USA) ～","pedigree_crosses":"サンデーサイレンス(USA) ：S3×M3","netkeiba_id":"2021101042","jbis_id":"0001335287","trainer":"田中道夫","affiliation":"(西 脇)","trainer_region":"地方","owner":"（同）ＪＰＮ技研","breeder":"天羽牧場","birthplace":"日高町","career_summary":"39戦0勝 [ 0-4-4-31 ]","major_win":"","earnings_netkeiba":460.2,"earnings_jbis":460.2,"last_race":"2026 園田 C３","last_finish":8,"hkjc_name_zh":null,"name_en":"Shonan Mantle","search_aliases":"Shonan Mantle","achievement_class":"未勝利","dam_birth_date":"2009-03-15","dam_birth_year":2009,"foal_birth_date":"2021-01-10","dam_age_at_foaling":11,"dam_age_precision":"exact","foal_order":2,"dam_netkeiba_id":"2009102124","dam_jbis_id":"0001110861","dam_career_summary":"26戦2勝 [ 2-6-1-17 ]","dam_earnings":3290.0,"dam_major_win":"13'4歳以上500万下","dam_known_foals":2,"dam_known_winners":0,"dam_known_graded_winners":0,"dam_siblings_json":"[{\"name\":\"ショウナンアキドン\",\"birth_year\":2020,\"sire\":\"ドゥラメンテ\",\"achievement_class\":\"未勝利\",\"earnings\":1554.2}]","dam_other_sire_foals_json":"[]","dam_metadata_source":"https://db.netkeiba.com/horse/2009102124/","dam_metadata_status":"profile_fetched","owner_id":"165803","owner_color_url":null},"sources":[{"source":"jbis","source_horse_id":"0001335287","url":"https://www.jbis.or.jp/horse/0001335287/","fetched_at":"2026-07-06T04:11:20.549323+00:00","data":{"affiliation":"(西 脇)","birth_year":2021,"breeder":"天羽牧場","breeder_url":"https://www.jbis.or.jp/breeder/0000001120/","bucket":"0000","dam":"セシリア","dam_id":"0001110861","earnings":460.2,"horse_id":"0001335287","horse_url":"https://www.jbis.or.jp/horse/0001335287/","last_finish":8,"last_race":"2026 園田 C３","last_race_url":"https://www.jbis.or.jp/race/result/20260625/227/06/","name":"ショウナンマントル","raw":["ショウナンマントル","2021","セン","セシリア","田中 道夫 (西 脇)","天羽牧場","460.2万円","2026 園田 C３","8"],"sex":"セン","sire":"ドゥラメンテ","source":"jbis","source_url":"https://www.jbis.or.jp/horse/0001151936/sire/progeny/?year=0000&belong=0&sort=name&items=100&page=1&order=A","trainer":"田中 道夫"}},{"source":"jbis","source_horse_id":"0001335287","url":"https://www.jbis.or.jp/horse/0001335287/","fetched_at":"2026-07-06T04:11:20.549323+00:00","data":{"affiliation":"(西 脇)","birth_year":2021,"breeder":"天羽牧場","breeder_url":"https://www.jbis.or.jp/breeder/0000001120/","bucket":"2021","dam":"セシリア","dam_id":"0001110861","earnings":460.2,"horse_id":"0001335287","horse_url":"https://www.jbis.or.jp/horse/0001335287/","last_finish":8,"last_race":"2026 園田 C３","last_race_url":"https://www.jbis.or.jp/race/result/20260625/227/06/","name":"ショウナンマントル","raw":["ショウナンマントル","2021","セン","セシリア","田中 道夫 (西 脇)","天羽牧場","460.2万円","2026 園田 C３","8"],"sex":"セン","sire":"ドゥラメンテ","source":"jbis","source_url":"https://www.jbis.or.jp/horse/0001151936/sire/progeny/?year=2021&belong=0&sort=name&items=100&page=1&order=A","trainer":"田中 道夫"}},{"source":"netkeiba","source_horse_id":"2021101042","url":"https://db.netkeiba.com/horse/2021101042/","fetched_at":"2026-07-06T04:11:20.549323+00:00","data":{"affiliation":"地","birth_year":2021,"breeder":"天羽牧場","broodmare_sire":"アグネスタキオン","broodmare_sire_id":"1998101516","dam":"セシリア","dam_id":"2009102124","earnings":460.2,"horse_id":"2021101042","horse_url":"https://db.netkeiba.com/horse/2021101042/","name":"ショウナンマントル","owner":"（同）ＪＰＮ技研","raw":["","ショウナンマントル","セ","2021","[血] [掲] [写]","[地] 田中道夫","ドゥラメンテ [ ]","セシリア [ ]","アグネスタキオン [ ]","（同）ＪＰＮ技研","天羽牧場","460.2"],"sex":"セ","sire":"ドゥラメンテ","source":"netkeiba","source_url":"https://db.netkeiba.com/horse/list.html?sire_id=2012104511&range=all&page=18","trainer":"田中道夫"}}],"races":[{"source":"netkeiba","race_date":"2026/06/25","meeting":"園田","weather":"雨","race_no":6,"race_name":"C3","race_id":"202650062506","race_url":"https://db.netkeiba.com/race/202650062506/","field_size":10,"bracket":8,"horse_number":9,"odds":51.0,"popularity":5,"finish":8,"jockey":"山本咲希","carried_weight":57.0,"surface":"ダ","distance":"ダ820","distance_m":820,"track_condition":"不","time":"0:52.1","margin":"1.5","corners":"","pace":"","last_3f":null,"body_weight":"","winner_or_runner_up":"37.5","prize":null,"data":{"body_weight":"","bracket":8,"carried_weight":57.0,"corners":"","distance":"ダ820","distance_m":820,"field_size":10,"finish":8,"horse_id":348,"horse_name":"ショウナンマントル","horse_number":9,"jockey":"山本咲希","last_3f":null,"margin":"1.5","meeting":"園田","netkeiba_id":"2021101042","odds":51.0,"pace":"","popularity":5,"prize":null,"race_date":"2026/06/25","race_id":"202650062506","race_name":"C3","race_no":6,"race_url":"https://db.netkeiba.com/race/202650062506/","raw":["2026/06/25","園田","雨","6","C3","","10","8","9","51.0","5","8","山本咲希","57","ダ820","","不","-18","0:52.1","1.5","11","","","","","6-6","25.6-36.3","37.5","439(-15)","","","メイショウコウラン",""],"source":"netkeiba","surface":"ダ","time":"0:52.1","track_condition":"不","weather":"雨","winner_or_runner_up":"37.5"}},{"source":"netkeiba","race_date":"2026/01/28","meeting":"姫路","weather":"晴","race_no":6,"race_name":"C3一","race_id":"202651012806","race_url":"https://db.netkeiba.com/race/202651012806/","field_size":10,"bracket":1,"horse_number":1,"odds":33.5,"popularity":7,"finish":8,"jockey":"永井孝典","carried_weight":57.0,"surface":"ダ","distance":"ダ800","distance_m":800,"track_condition":"良","time":"0:52.9","margin":"1.6","corners":"","pace":"","last_3f":null,"body_weight":"","winner_or_runner_up":"38.6","prize":null,"data":{"body_weight":"","bracket":1,"carried_weight":57.0,"corners":"","distance":"ダ800","distance_m":800,"field_size":10,"finish":8,"horse_id":348,"horse_name":"ショウナンマントル","horse_number":1,"jockey":"永井孝典","last_3f":null,"margin":"1.6","meeting":"姫路","netkeiba_id":"2021101042","odds":33.5,"pace":"","popularity":7,"prize":null,"race_date":"2026/01/28","race_id":"202651012806","race_name":"C3一","race_no":6,"race_url":"https://db.netkeiba.com/race/202651012806/","raw":["2026/01/28","姫路","晴","6","C3一","","10","1","1","33.5","7","8","永井孝典","57","ダ800","","良","**","0:52.9","1.6","**","","","","","10-8","","38.6","454(0)","","","ヴェニスクィーン",""],"source":"netkeiba","surface":"ダ","time":"0:52.9","track_condition":"良","weather":"晴","winner_or_runner_up":"38.6"}},{"source":"netkeiba","race_date":"2025/12/30","meeting":"園田","weather":"曇","race_no":6,"race_name":"C3一","race_id":"202550123006","race_url":"https://db.netkeiba.com/race/202550123006/","field_size":12,"bracket":7,"horse_number":9,"odds":37.2,"popularity":9,"finish":3,"jockey":"山本咲希","carried_weight":57.0,"surface":"ダ","distance":"ダ820","distance_m":820,"track_condition":"稍","time":"0:52.2","margin":"0.2","corners":"","pace":"","last_3f":null,"body_weight":"","winner_or_runner_up":"37.5","prize":null,"data":{"body_weight":"","bracket":7,"carried_weight":57.0,"corners":"","distance":"ダ820","distance_m":820,"field_size":12,"finish":3,"horse_id":348,"horse_name":"ショウナンマントル","horse_number":9,"jockey":"山本咲希","last_3f":null,"margin":"0.2","meeting":"園田","netkeiba_id":"2021101042","odds":37.2,"pace":"","popularity":9,"prize":null,"race_date":"2025/12/30","race_id":"202550123006","race_name":"C3一","race_no":6,"race_url":"https://db.netkeiba.com/race/202550123006/","raw":["2025/12/30","園田","曇","6","C3一","","12","7","9","37.2","9","3","山本咲希","57","ダ820","","稍","**","0:52.2","0.2","**","","","","","6-8","","37.5","454(-7)","","","シロズキンチャン","15.0"],"source":"netkeiba","surface":"ダ","time":"0:52.2","track_condition":"稍","weather":"曇","winner_or_runner_up":"37.5"}},{"source":"netkeiba","race_date":"2025/11/26","meeting":"園田","weather":"曇","race_no":4,"race_name":"合山町ダッシュC3","race_id":"202550112604","race_url":"https://db.netkeiba.com/race/202550112604/","field_size":12,"bracket":5,"horse_number":5,"odds":27.6,"popularity":7,"finish":5,"jockey":"山本咲希","carried_weight":57.0,"surface":"ダ","distance":"ダ820","distance_m":820,"track_condition":"稍","time":"0:52.4","margin":"0.9","corners":"","pace":"","last_3f":null,"body_weight":"","winner_or_runner_up":"37.7","prize":null,"data":{"body_weight":"","bracket":5,"carried_weight":57.0,"corners":"","distance":"ダ820","distance_m":820,"field_size":12,"finish":5,"horse_id":348,"horse_name":"ショウナンマントル","horse_number":5,"jockey":"山本咲希","last_3f":null,"margin":"0.9","meeting":"園田","netkeiba_id":"2021101042","odds":27.6,"pace":"","popularity":7,"prize":null,"race_date":"2025/11/26","race_id":"202550112604","race_name":"合山町ダッシュC3","race_no":4,"race_url":"https://db.netkeiba.com/race/202550112604/","raw":["2025/11/26","園田","曇","4","合山町ダッシュC3","","12","5","5","27.6","7","5","山本咲希","57","ダ820","","稍","**","0:52.4","0.9","**","","","","","4-3","","37.7","461(+1)","","","イエローキャブ","6.0"],"source":"netkeiba","surface":"ダ","time":"0:52.4","track_condition":"稍","weather":"曇","winner_or_runner_up":"37.7"}},{"source":"netkeiba","race_date":"2025/11/04","meeting":"園田","weather":"晴","race_no":5,"race_name":"パカやろう!霜月の蹄(C2)","race_id":"202550110405","race_url":"https://db.netkeiba.com/race/202550110405/","field_size":12,"bracket":4,"horse_number":4,"odds":337.1,"popularity":11,"finish":9,"jockey":"山本咲希","carried_weight":57.0,"surface":"ダ","distance":"ダ820","distance_m":820,"track_condition":"稍","time":"0:52.3","margin":"1.4","corners":"","pace":"","last_3f":null,"body_weight":"","winner_or_runner_up":"37.5","prize":null,"data":{"body_weight":"","bracket":4,"carried_weight":57.0,"corners":"","distance":"ダ820","distance_m":820,"field_size":12,"finish":9,"horse_id":348,"horse_name":"ショウナンマントル","horse_number":4,"jockey":"山本咲希","last_3f":null,"margin":"1.4","meeting":"園田","netkeiba_id":"2021101042","odds":337.1,"pace":"","popularity":11,"prize":null,"race_date":"2025/11/04","race_id":"202550110405","race_name":"パカやろう!霜月の蹄(C2)","race_no":5,"race_url":"https://db.netkeiba.com/race/202550110405/","raw":["2025/11/04","園田","晴","5","パカやろう!霜月の蹄(C2)","","12","4","4","337.1","11","9","山本咲希","57","ダ820","","稍","**","0:52.3","1.4","**","","","","","9-8","","37.5","460(+5)","","","イッツマイビジネス",""],"source":"netkeiba","surface":"ダ","time":"0:52.3","track_condition":"稍","weather":"晴","winner_or_runner_up":"37.5"}},{"source":"netkeiba","race_date":"2025/10/15","meeting":"園田","weather":"曇","race_no":5,"race_name":"聚遠亭ダッシュC2二","race_id":"202550101505","race_url":"https://db.netkeiba.com/race/202550101505/","field_size":12,"bracket":6,"horse_number":7,"odds":70.6,"popularity":8,"finish":9,"jockey":"中田貴士","carried_weight":57.0,"surface":"ダ","distance":"ダ820","distance_m":820,"track_condition":"良","time":"0:52.3","margin":"1.4","corners":"","pace":"","last_3f":null,"body_weight":"","winner_or_runner_up":"36.3","prize":null,"data":{"body_weight":"","bracket":6,"carried_weight":57.0,"corners":"","distance":"ダ820","distance_m":820,"field_size":12,"finish":9,"horse_id":348,"horse_name":"ショウナンマントル","horse_number":7,"jockey":"中田貴士","last_3f":null,"margin":"1.4","meeting":"園田","netkeiba_id":"2021101042","odds":70.6,"pace":"","popularity":8,"prize":null,"race_date":"2025/10/15","race_id":"202550101505","race_name":"聚遠亭ダッシュC2二","race_no":5,"race_url":"https://db.netkeiba.com/race/202550101505/","raw":["2025/10/15","園田","曇","5","聚遠亭ダッシュC2二","","12","6","7","70.6","8","9","中田貴士","57","ダ820","","良","**","0:52.3","1.4","**","","","","","11-11","","36.3","455(-1)","","","アーニャワクワク",""],"source":"netkeiba","surface":"ダ","time":"0:52.3","track_condition":"良","weather":"曇","winner_or_runner_up":"36.3"}},{"source":"netkeiba","race_date":"2025/10/01","meeting":"園田","weather":"晴","race_no":12,"race_name":"C2一","race_id":"202550100112","race_url":"https://db.netkeiba.com/race/202550100112/","field_size":12,"bracket":8,"horse_number":12,"odds":31.5,"popularity":6,"finish":7,"jockey":"高橋愛叶","carried_weight":56.0,"surface":"ダ","distance":"ダ820","distance_m":820,"track_condition":"稍","time":"0:52.4","margin":"1.0","corners":"","pace":"","last_3f":null,"body_weight":"","winner_or_runner_up":"37.4","prize":null,"data":{"body_weight":"","bracket":8,"carried_weight":56.0,"corners":"","distance":"ダ820","distance_m":820,"field_size":12,"finish":7,"horse_id":348,"horse_name":"ショウナンマントル","horse_number":12,"jockey":"高橋愛叶","last_3f":null,"margin":"1.0","meeting":"園田","netkeiba_id":"2021101042","odds":31.5,"pace":"","popularity":6,"prize":null,"race_date":"2025/10/01","race_id":"202550100112","race_name":"C2一","race_no":12,"race_url":"https://db.netkeiba.com/race/202550100112/","raw":["2025/10/01","園田","晴","12","C2一","","12","8","12","31.5","6","7","高橋愛叶","56","ダ820","","稍","**","0:52.4","1.0","**","","","","","8-10","","37.4","456(+7)","","","ファイブレイナ",""],"source":"netkeiba","surface":"ダ","time":"0:52.4","track_condition":"稍","weather":"晴","winner_or_runner_up":"37.4"}},{"source":"netkeiba","race_date":"2025/09/04","meeting":"園田","weather":"曇","race_no":6,"race_name":"C2一","race_id":"202550090406","race_url":"https://db.netkeiba.com/race/202550090406/","field_size":12,"bracket":7,"horse_number":9,"odds":9.2,"popularity":5,"finish":4,"jockey":"山本咲希","carried_weight":57.0,"surface":"ダ","distance":"ダ820","distance_m":820,"track_condition":"良","time":"0:51.7","margin":"0.7","corners":"","pace":"","last_3f":null,"body_weight":"","winner_or_runner_up":"37.1","prize":null,"data":{"body_weight":"","bracket":7,"carried_weight":57.0,"corners":"","distance":"ダ820","distance_m":820,"field_size":12,"finish":4,"horse_id":348,"horse_name":"ショウナンマントル","horse_number":9,"jockey":"山本咲希","last_3f":null,"margin":"0.7","meeting":"園田","netkeiba_id":"2021101042","odds":9.2,"pace":"","popularity":5,"prize":null,"race_date":"2025/09/04","race_id":"202550090406","race_name":"C2一","race_no":6,"race_url":"https://db.netkeiba.com/race/202550090406/","raw":["2025/09/04","園田","曇","6","C2一","","12","7","9","9.2","5","4","山本咲希","57","ダ820","","良","**","0:51.7","0.7","**","","","","","4-4","","37.1","449(0)","","","ヴァンセゾニエ","12.0"],"source":"netkeiba","surface":"ダ","time":"0:51.7","track_condition":"良","weather":"曇","winner_or_runner_up":"37.1"}},{"source":"netkeiba","race_date":"2025/08/13","meeting":"園田","weather":"曇","race_no":1,"race_name":"夏休みそのだけいばで(C2)","race_id":"202550081301","race_url":"https://db.netkeiba.com/race/202550081301/","field_size":12,"bracket":5,"horse_number":5,"odds":19.2,"popularity":5,"finish":8,"jockey":"山本咲希","carried_weight":57.0,"surface":"ダ","distance":"ダ1400","distance_m":1400,"track_condition":"稍","time":"1:35.9","margin":"2.9","corners":"","pace":"","last_3f":null,"body_weight":"","winner_or_runner_up":"44.1","prize":null,"data":{"body_weight":"","bracket":5,"carried_weight":57.0,"corners":"","distance":"ダ1400","distance_m":1400,"field_size":12,"finish":8,"horse_id":348,"horse_name":"ショウナンマントル","horse_number":5,"jockey":"山本咲希","last_3f":null,"margin":"2.9","meeting":"園田","netkeiba_id":"2021101042","odds":19.2,"pace":"","popularity":5,"prize":null,"race_date":"2025/08/13","race_id":"202550081301","race_name":"夏休みそのだけいばで(C2)","race_no":1,"race_url":"https://db.netkeiba.com/race/202550081301/","raw":["2025/08/13","園田","曇","1","夏休みそのだけいばで(C2)","","12","5","5","19.2","5","8","山本咲希","57","ダ1400","","稍","**","1:35.9","2.9","**","","","","","2-2-4-4","","44.1","449(+5)","","","シュトローム",""],"source":"netkeiba","surface":"ダ","time":"1:35.9","track_condition":"稍","weather":"曇","winner_or_runner_up":"44.1"}},{"source":"netkeiba","race_date":"2025/07/24","meeting":"園田","weather":"晴","race_no":7,"race_name":"C2二","race_id":"202550072407","race_url":"https://db.netkeiba.com/race/202550072407/","field_size":12,"bracket":8,"horse_number":12,"odds":20.4,"popularity":7,"finish":3,"jockey":"山本咲希","carried_weight":57.0,"surface":"ダ","distance":"ダ820","distance_m":820,"track_condition":"良","time":"0:51.3","margin":"0.2","corners":"","pace":"","last_3f":null,"body_weight":"","winner_or_runner_up":"36.9","prize":null,"data":{"body_weight":"","bracket":8,"carried_weight":57.0,"corners":"","distance":"ダ820","distance_m":820,"field_size":12,"finish":3,"horse_id":348,"horse_name":"ショウナンマントル","horse_number":12,"jockey":"山本咲希","last_3f":null,"margin":"0.2","meeting":"園田","netkeiba_id":"2021101042","odds":20.4,"pace":"","popularity":7,"prize":null,"race_date":"2025/07/24","race_id":"202550072407","race_name":"C2二","race_no":7,"race_url":"https://db.netkeiba.com/race/202550072407/","raw":["2025/07/24","園田","晴","7","C2二","","12","8","12","20.4","7","3","山本咲希","57","ダ820","","良","**","0:51.3","0.2","**","","","","","6-6","","36.9","444(+4)","","","フェアリータイザン","17.5"],"source":"netkeiba","surface":"ダ","time":"0:51.3","track_condition":"良","weather":"晴","winner_or_runner_up":"36.9"}},{"source":"netkeiba","race_date":"2025/07/09","meeting":"園田","weather":"晴","race_no":7,"race_name":"C2二","race_id":"202550070907","race_url":"https://db.netkeiba.com/race/202550070907/","field_size":10,"bracket":6,"horse_number":6,"odds":80.9,"popularity":7,"finish":7,"jockey":"山本咲希","carried_weight":57.0,"surface":"ダ","distance":"ダ1400","distance_m":1400,"track_condition":"良","time":"1:33.3","margin":"1.5","corners":"","pace":"","last_3f":null,"body_weight":"","winner_or_runner_up":"41.5","prize":null,"data":{"body_weight":"","bracket":6,"carried_weight":57.0,"corners":"","distance":"ダ1400","distance_m":1400,"field_size":10,"finish":7,"horse_id":348,"horse_name":"ショウナンマントル","horse_number":6,"jockey":"山本咲希","last_3f":null,"margin":"1.5","meeting":"園田","netkeiba_id":"2021101042","odds":80.9,"pace":"","popularity":7,"prize":null,"race_date":"2025/07/09","race_id":"202550070907","race_name":"C2二","race_no":7,"race_url":"https://db.netkeiba.com/race/202550070907/","raw":["2025/07/09","園田","晴","7","C2二","","10","6","6","80.9","7","7","山本咲希","57","ダ1400","","良","**","1:33.3","1.5","**","","","","","4-4-6-6","","41.5","440(-6)","","","ヴォーパルソード",""],"source":"netkeiba","surface":"ダ","time":"1:33.3","track_condition":"良","weather":"晴","winner_or_runner_up":"41.5"}},{"source":"netkeiba","race_date":"2025/06/27","meeting":"園田","weather":"晴","race_no":8,"race_name":"ダリア賞C2二","race_id":"202550062708","race_url":"https://db.netkeiba.com/race/202550062708/","field_size":7,"bracket":5,"horse_number":5,"odds":22.7,"popularity":6,"finish":3,"jockey":"山本咲希","carried_weight":57.0,"surface":"ダ","distance":"ダ1400","distance_m":1400,"track_condition":"稍","time":"1:34.5","margin":"0.4","corners":"","pace":"","last_3f":null,"body_weight":"","winner_or_runner_up":"42.1","prize":null,"data":{"body_weight":"","bracket":5,"carried_weight":57.0,"corners":"","distance":"ダ1400","distance_m":1400,"field_size":7,"finish":3,"horse_id":348,"horse_name":"ショウナンマントル","horse_number":5,"jockey":"山本咲希","last_3f":null,"margin":"0.4","meeting":"園田","netkeiba_id":"2021101042","odds":22.7,"pace":"","popularity":6,"prize":null,"race_date":"2025/06/27","race_id":"202550062708","race_name":"ダリア賞C2二","race_no":8,"race_url":"https://db.netkeiba.com/race/202550062708/","raw":["2025/06/27","園田","晴","8","ダリア賞C2二","","7","5","5","22.7","6","3","山本咲希","57","ダ1400","","稍","**","1:34.5","0.4","**","","","","","3-3-3-3","","42.1","446(-8)","","","オノマトペ","17.5"],"source":"netkeiba","surface":"ダ","time":"1:34.5","track_condition":"稍","weather":"晴","winner_or_runner_up":"42.1"}},{"source":"netkeiba","race_date":"2025/03/26","meeting":"園田","weather":"晴","race_no":6,"race_name":"C2一","race_id":"202550032606","race_url":"https://db.netkeiba.com/race/202550032606/","field_size":12,"bracket":1,"horse_number":1,"odds":109.1,"popularity":11,"finish":11,"jockey":"中田貴士","carried_weight":56.0,"surface":"ダ","distance":"ダ1400","distance_m":1400,"track_condition":"良","time":"1:33.4","margin":"1.9","corners":"","pace":"","last_3f":null,"body_weight":"","winner_or_runner_up":"40.5","prize":null,"data":{"body_weight":"","bracket":1,"carried_weight":56.0,"corners":"","distance":"ダ1400","distance_m":1400,"field_size":12,"finish":11,"horse_id":348,"horse_name":"ショウナンマントル","horse_number":1,"jockey":"中田貴士","last_3f":null,"margin":"1.9","meeting":"園田","netkeiba_id":"2021101042","odds":109.1,"pace":"","popularity":11,"prize":null,"race_date":"2025/03/26","race_id":"202550032606","race_name":"C2一","race_no":6,"race_url":"https://db.netkeiba.com/race/202550032606/","raw":["2025/03/26","園田","晴","6","C2一","","12","1","1","109.1","11","11","中田貴士","56","ダ1400","","良","**","1:33.4","1.9","**","","","","","10-10-12-12","","40.5","454(-1)","","","ベストディシジョン",""],"source":"netkeiba","surface":"ダ","time":"1:33.4","track_condition":"良","weather":"晴","winner_or_runner_up":"40.5"}},{"source":"netkeiba","race_date":"2025/03/11","meeting":"園田","weather":"雨","race_no":5,"race_name":"DASHーPayマン(C2)","race_id":"202550031105","race_url":"https://db.netkeiba.com/race/202550031105/","field_size":10,"bracket":8,"horse_number":10,"odds":45.5,"popularity":6,"finish":3,"jockey":"中田貴士","carried_weight":56.0,"surface":"ダ","distance":"ダ1400","distance_m":1400,"track_condition":"重","time":"1:35.1","margin":"0.7","corners":"","pace":"","last_3f":null,"body_weight":"","winner_or_runner_up":"41.0","prize":null,"data":{"body_weight":"","bracket":8,"carried_weight":56.0,"corners":"","distance":"ダ1400","distance_m":1400,"field_size":10,"finish":3,"horse_id":348,"horse_name":"ショウナンマントル","horse_number":10,"jockey":"中田貴士","last_3f":null,"margin":"0.7","meeting":"園田","netkeiba_id":"2021101042","odds":45.5,"pace":"","popularity":6,"prize":null,"race_date":"2025/03/11","race_id":"202550031105","race_name":"DASHーPayマン(C2)","race_no":5,"race_url":"https://db.netkeiba.com/race/202550031105/","raw":["2025/03/11","園田","雨","5","DASHーPayマン(C2)","","10","8","10","45.5","6","3","中田貴士","56","ダ1400","","重","**","1:35.1","0.7","**","","","","","3-3-2-3","","41.0","455(+3)","","","ロードシャマール","14.0"],"source":"netkeiba","surface":"ダ","time":"1:35.1","track_condition":"重","weather":"雨","winner_or_runner_up":"41.0"}},{"source":"netkeiba","race_date":"2025/02/26","meeting":"姫路","weather":"晴","race_no":6,"race_name":"C2二","race_id":"202551022606","race_url":"https://db.netkeiba.com/race/202551022606/","field_size":8,"bracket":4,"horse_number":4,"odds":36.6,"popularity":6,"finish":2,"jockey":"中田貴士","carried_weight":56.0,"surface":"ダ","distance":"ダ1400","distance_m":1400,"track_condition":"良","time":"1:35.9","margin":"0.9","corners":"","pace":"","last_3f":null,"body_weight":"","winner_or_runner_up":"39.6","prize":null,"data":{"body_weight":"","bracket":4,"carried_weight":56.0,"corners":"","distance":"ダ1400","distance_m":1400,"field_size":8,"finish":2,"horse_id":348,"horse_name":"ショウナンマントル","horse_number":4,"jockey":"中田貴士","last_3f":null,"margin":"0.9","meeting":"姫路","netkeiba_id":"2021101042","odds":36.6,"pace":"","popularity":6,"prize":null,"race_date":"2025/02/26","race_id":"202551022606","race_name":"C2二","race_no":6,"race_url":"https://db.netkeiba.com/race/202551022606/","raw":["2025/02/26","姫路","晴","6","C2二","","8","4","4","36.6","6","2","中田貴士","56","ダ1400","","良","**","1:35.9","0.9","**","","","","","3-3-4-3","","39.6","452(-2)","","","エリカヴェローナ","24.5"],"source":"netkeiba","surface":"ダ","time":"1:35.9","track_condition":"良","weather":"晴","winner_or_runner_up":"39.6"}},{"source":"netkeiba","race_date":"2025/02/13","meeting":"姫路","weather":"曇","race_no":6,"race_name":"C2一","race_id":"202551021306","race_url":"https://db.netkeiba.com/race/202551021306/","field_size":12,"bracket":8,"horse_number":12,"odds":131.2,"popularity":11,"finish":9,"jockey":"中田貴士","carried_weight":56.0,"surface":"ダ","distance":"ダ1400","distance_m":1400,"track_condition":"稍","time":"1:36.0","margin":"1.5","corners":"","pace":"","last_3f":null,"body_weight":"","winner_or_runner_up":"42.2","prize":null,"data":{"body_weight":"","bracket":8,"carried_weight":56.0,"corners":"","distance":"ダ1400","distance_m":1400,"field_size":12,"finish":9,"horse_id":348,"horse_name":"ショウナンマントル","horse_number":12,"jockey":"中田貴士","last_3f":null,"margin":"1.5","meeting":"姫路","netkeiba_id":"2021101042","odds":131.2,"pace":"","popularity":11,"prize":null,"race_date":"2025/02/13","race_id":"202551021306","race_name":"C2一","race_no":6,"race_url":"https://db.netkeiba.com/race/202551021306/","raw":["2025/02/13","姫路","曇","6","C2一","","12","8","12","131.2","11","9","中田貴士","56","ダ1400","","稍","**","1:36.0","1.5","**","","","","","1-3-3-4","","42.2","454(+1)","","","ナムラオリビア",""],"source":"netkeiba","surface":"ダ","time":"1:36.0","track_condition":"稍","weather":"曇","winner_or_runner_up":"42.2"}},{"source":"netkeiba","race_date":"2025/01/30","meeting":"姫路","weather":"晴","race_no":4,"race_name":"佐良和7ハロンC2二","race_id":"202551013004","race_url":"https://db.netkeiba.com/race/202551013004/","field_size":10,"bracket":5,"horse_number":5,"odds":60.3,"popularity":7,"finish":4,"jockey":"大柿一真","carried_weight":56.0,"surface":"ダ","distance":"ダ1400","distance_m":1400,"track_condition":"良","time":"1:35.9","margin":"1.1","corners":"","pace":"","last_3f":null,"body_weight":"","winner_or_runner_up":"43.0","prize":null,"data":{"body_weight":"","bracket":5,"carried_weight":56.0,"corners":"","distance":"ダ1400","distance_m":1400,"field_size":10,"finish":4,"horse_id":348,"horse_name":"ショウナンマントル","horse_number":5,"jockey":"大柿一真","last_3f":null,"margin":"1.1","meeting":"姫路","netkeiba_id":"2021101042","odds":60.3,"pace":"","popularity":7,"prize":null,"race_date":"2025/01/30","race_id":"202551013004","race_name":"佐良和7ハロンC2二","race_no":4,"race_url":"https://db.netkeiba.com/race/202551013004/","raw":["2025/01/30","姫路","晴","4","佐良和7ハロンC2二","","10","5","5","60.3","7","4","大柿一真","56","ダ1400","","良","**","1:35.9","1.1","**","","","","","5-5-4-3","","43.0","453(-1)","","","スティールアグネス","10.5"],"source":"netkeiba","surface":"ダ","time":"1:35.9","track_condition":"良","weather":"晴","winner_or_runner_up":"43.0"}},{"source":"netkeiba","race_date":"2025/01/16","meeting":"園田","weather":"晴","race_no":5,"race_name":"ありがとう西宮ホルモ(C2)","race_id":"202550011605","race_url":"https://db.netkeiba.com/race/202550011605/","field_size":11,"bracket":5,"horse_number":6,"odds":30.0,"popularity":6,"finish":5,"jockey":"中田貴士","carried_weight":56.0,"surface":"ダ","distance":"ダ1400","distance_m":1400,"track_condition":"良","time":"1:34.9","margin":"1.3","corners":"","pace":"","last_3f":null,"body_weight":"","winner_or_runner_up":"42.0","prize":null,"data":{"body_weight":"","bracket":5,"carried_weight":56.0,"corners":"","distance":"ダ1400","distance_m":1400,"field_size":11,"finish":5,"horse_id":348,"horse_name":"ショウナンマントル","horse_number":6,"jockey":"中田貴士","last_3f":null,"margin":"1.3","meeting":"園田","netkeiba_id":"2021101042","odds":30.0,"pace":"","popularity":6,"prize":null,"race_date":"2025/01/16","race_id":"202550011605","race_name":"ありがとう西宮ホルモ(C2)","race_no":5,"race_url":"https://db.netkeiba.com/race/202550011605/","raw":["2025/01/16","園田","晴","5","ありがとう西宮ホルモ(C2)","","11","5","6","30.0","6","5","中田貴士","56","ダ1400","","良","**","1:34.9","1.3","**","","","","","5-5-5-7","","42.0","454(0)","","","ロードシャマール","7.0"],"source":"netkeiba","surface":"ダ","time":"1:34.9","track_condition":"良","weather":"晴","winner_or_runner_up":"42.0"}},{"source":"netkeiba","race_date":"2024/12/30","meeting":"園田","weather":"曇","race_no":4,"race_name":"大掃除ブレイクタイム(C3)","race_id":"202450123004","race_url":"https://db.netkeiba.com/race/202450123004/","field_size":10,"bracket":5,"horse_number":5,"odds":3.8,"popularity":1,"finish":2,"jockey":"中田貴士","carried_weight":56.0,"surface":"ダ","distance":"ダ1230","distance_m":1230,"track_condition":"良","time":"1:23.0","margin":"0.0","corners":"","pace":"","last_3f":null,"body_weight":"","winner_or_runner_up":"40.1","prize":null,"data":{"body_weight":"","bracket":5,"carried_weight":56.0,"corners":"","distance":"ダ1230","distance_m":1230,"field_size":10,"finish":2,"horse_id":348,"horse_name":"ショウナンマントル","horse_number":5,"jockey":"中田貴士","last_3f":null,"margin":"0.0","meeting":"園田","netkeiba_id":"2021101042","odds":3.8,"pace":"","popularity":1,"prize":null,"race_date":"2024/12/30","race_id":"202450123004","race_name":"大掃除ブレイクタイム(C3)","race_no":4,"race_url":"https://db.netkeiba.com/race/202450123004/","raw":["2024/12/30","園田","曇","4","大掃除ブレイクタイム(C3)","","10","5","5","3.8","1","2","中田貴士","56","ダ1230","","良","**","1:23.0","0.0","**","","","","","9-9-4-1","","40.1","454(+1)","","","ワンダーアウメント","19.6"],"source":"netkeiba","surface":"ダ","time":"1:23.0","track_condition":"良","weather":"曇","winner_or_runner_up":"40.1"}},{"source":"netkeiba","race_date":"2024/12/17","meeting":"園田","weather":"晴","race_no":5,"race_name":"大豆山町スプリントC(C3)","race_id":"202450121705","race_url":"https://db.netkeiba.com/race/202450121705/","field_size":12,"bracket":7,"horse_number":10,"odds":23.4,"popularity":6,"finish":2,"jockey":"中田貴士","carried_weight":56.0,"surface":"ダ","distance":"ダ1230","distance_m":1230,"track_condition":"良","time":"1:22.4","margin":"0.7","corners":"","pace":"","last_3f":null,"body_weight":"","winner_or_runner_up":"40.4","prize":null,"data":{"body_weight":"","bracket":7,"carried_weight":56.0,"corners":"","distance":"ダ1230","distance_m":1230,"field_size":12,"finish":2,"horse_id":348,"horse_name":"ショウナンマントル","horse_number":10,"jockey":"中田貴士","last_3f":null,"margin":"0.7","meeting":"園田","netkeiba_id":"2021101042","odds":23.4,"pace":"","popularity":6,"prize":null,"race_date":"2024/12/17","race_id":"202450121705","race_name":"大豆山町スプリントC(C3)","race_no":5,"race_url":"https://db.netkeiba.com/race/202450121705/","raw":["2024/12/17","園田","晴","5","大豆山町スプリントC(C3)","","12","7","10","23.4","6","2","中田貴士","56","ダ1230","","良","**","1:22.4","0.7","**","","","","","6-6-3-2","","40.4","453(+2)","","","ゴッドホーネット","19.6"],"source":"netkeiba","surface":"ダ","time":"1:22.4","track_condition":"良","weather":"晴","winner_or_runner_up":"40.4"}},{"source":"netkeiba","race_date":"2024/11/27","meeting":"園田","weather":"曇","race_no":5,"race_name":"三刀屋7ハロンC3一","race_id":"202450112705","race_url":"https://db.netkeiba.com/race/202450112705/","field_size":10,"bracket":1,"horse_number":1,"odds":27.2,"popularity":8,"finish":9,"jockey":"中田貴士","carried_weight":56.0,"surface":"ダ","distance":"ダ1400","distance_m":1400,"track_condition":"重","time":"1:37.1","margin":"2.7","corners":"","pace":"","last_3f":null,"body_weight":"","winner_or_runner_up":"44.4","prize":null,"data":{"body_weight":"","bracket":1,"carried_weight":56.0,"corners":"","distance":"ダ1400","distance_m":1400,"field_size":10,"finish":9,"horse_id":348,"horse_name":"ショウナンマントル","horse_number":1,"jockey":"中田貴士","last_3f":null,"margin":"2.7","meeting":"園田","netkeiba_id":"2021101042","odds":27.2,"pace":"","popularity":8,"prize":null,"race_date":"2024/11/27","race_id":"202450112705","race_name":"三刀屋7ハロンC3一","race_no":5,"race_url":"https://db.netkeiba.com/race/202450112705/","raw":["2024/11/27","園田","曇","5","三刀屋7ハロンC3一","","10","1","1","27.2","8","9","中田貴士","56","ダ1400","","重","**","1:37.1","2.7","**","","","","","5-3-5-5","","44.4","451(+2)","","","プロミット",""],"source":"netkeiba","surface":"ダ","time":"1:37.1","track_condition":"重","weather":"曇","winner_or_runner_up":"44.4"}},{"source":"netkeiba","race_date":"2024/11/13","meeting":"園田","weather":"晴","race_no":3,"race_name":"C2三","race_id":"202450111303","race_url":"https://db.netkeiba.com/race/202450111303/","field_size":10,"bracket":8,"horse_number":9,"odds":86.1,"popularity":8,"finish":6,"jockey":"中田貴士","carried_weight":56.0,"surface":"ダ","distance":"ダ1400","distance_m":1400,"track_condition":"良","time":"1:34.2","margin":"0.4","corners":"","pace":"","last_3f":null,"body_weight":"","winner_or_runner_up":"41.0","prize":null,"data":{"body_weight":"","bracket":8,"carried_weight":56.0,"corners":"","distance":"ダ1400","distance_m":1400,"field_size":10,"finish":6,"horse_id":348,"horse_name":"ショウナンマントル","horse_number":9,"jockey":"中田貴士","last_3f":null,"margin":"0.4","meeting":"園田","netkeiba_id":"2021101042","odds":86.1,"pace":"","popularity":8,"prize":null,"race_date":"2024/11/13","race_id":"202450111303","race_name":"C2三","race_no":3,"race_url":"https://db.netkeiba.com/race/202450111303/","raw":["2024/11/13","園田","晴","3","C2三","","10","8","9","86.1","8","6","中田貴士","56","ダ1400","","良","**","1:34.2","0.4","**","","","","","3-3-3-4","","41.0","449(-4)","","","アンフィニレイス",""],"source":"netkeiba","surface":"ダ","time":"1:34.2","track_condition":"良","weather":"晴","winner_or_runner_up":"41.0"}},{"source":"netkeiba","race_date":"2024/10/30","meeting":"園田","weather":"晴","race_no":4,"race_name":"夏梅7ハロンC2二","race_id":"202450103004","race_url":"https://db.netkeiba.com/race/202450103004/","field_size":10,"bracket":6,"horse_number":6,"odds":46.5,"popularity":7,"finish":6,"jockey":"中田貴士","carried_weight":56.0,"surface":"ダ","distance":"ダ1400","distance_m":1400,"track_condition":"不","time":"1:35.8","margin":"2.6","corners":"","pace":"","last_3f":null,"body_weight":"","winner_or_runner_up":"42.5","prize":null,"data":{"body_weight":"","bracket":6,"carried_weight":56.0,"corners":"","distance":"ダ1400","distance_m":1400,"field_size":10,"finish":6,"horse_id":348,"horse_name":"ショウナンマントル","horse_number":6,"jockey":"中田貴士","last_3f":null,"margin":"2.6","meeting":"園田","netkeiba_id":"2021101042","odds":46.5,"pace":"","popularity":7,"prize":null,"race_date":"2024/10/30","race_id":"202450103004","race_name":"夏梅7ハロンC2二","race_no":4,"race_url":"https://db.netkeiba.com/race/202450103004/","raw":["2024/10/30","園田","晴","4","夏梅7ハロンC2二","","10","6","6","46.5","7","6","中田貴士","56","ダ1400","","不","**","1:35.8","2.6","**","","","","","5-5-5-4","","42.5","453(+2)","","","ディアフリーゼ",""],"source":"netkeiba","surface":"ダ","time":"1:35.8","track_condition":"不","weather":"晴","winner_or_runner_up":"42.5"}},{"source":"netkeiba","race_date":"2024/10/11","meeting":"園田","weather":"晴","race_no":10,"race_name":"コスモス賞C2","race_id":"202450101110","race_url":"https://db.netkeiba.com/race/202450101110/","field_size":10,"bracket":4,"horse_number":4,"odds":264.4,"popularity":9,"finish":9,"jockey":"中田貴士","carried_weight":56.0,"surface":"ダ","distance":"ダ1230","distance_m":1230,"track_condition":"良","time":"1:22.7","margin":"1.8","corners":"","pace":"","last_3f":null,"body_weight":"","winner_or_runner_up":"41.4","prize":null,"data":{"body_weight":"","bracket":4,"carried_weight":56.0,"corners":"","distance":"ダ1230","distance_m":1230,"field_size":10,"finish":9,"horse_id":348,"horse_name":"ショウナンマントル","horse_number":4,"jockey":"中田貴士","last_3f":null,"margin":"1.8","meeting":"園田","netkeiba_id":"2021101042","odds":264.4,"pace":"","popularity":9,"prize":null,"race_date":"2024/10/11","race_id":"202450101110","race_name":"コスモス賞C2","race_no":10,"race_url":"https://db.netkeiba.com/race/202450101110/","raw":["2024/10/11","園田","晴","10","コスモス賞C2","","10","4","4","264.4","9","9","中田貴士","56","ダ1230","","良","**","1:22.7","1.8","**","","","","","7-7-7-9","","41.4","451(+7)","","","デュアル",""],"source":"netkeiba","surface":"ダ","time":"1:22.7","track_condition":"良","weather":"晴","winner_or_runner_up":"41.4"}},{"source":"netkeiba","race_date":"2024/09/26","meeting":"園田","weather":"晴","race_no":12,"race_name":"C2","race_id":"202450092612","race_url":"https://db.netkeiba.com/race/202450092612/","field_size":11,"bracket":1,"horse_number":1,"odds":89.3,"popularity":9,"finish":8,"jockey":"中田貴士","carried_weight":55.0,"surface":"ダ","distance":"ダ1230","distance_m":1230,"track_condition":"良","time":"1:22.8","margin":"2.0","corners":"","pace":"","last_3f":null,"body_weight":"","winner_or_runner_up":"40.4","prize":null,"data":{"body_weight":"","bracket":1,"carried_weight":55.0,"corners":"","distance":"ダ1230","distance_m":1230,"field_size":11,"finish":8,"horse_id":348,"horse_name":"ショウナンマントル","horse_number":1,"jockey":"中田貴士","last_3f":null,"margin":"2.0","meeting":"園田","netkeiba_id":"2021101042","odds":89.3,"pace":"","popularity":9,"prize":null,"race_date":"2024/09/26","race_id":"202450092612","race_name":"C2","race_no":12,"race_url":"https://db.netkeiba.com/race/202450092612/","raw":["2024/09/26","園田","晴","12","C2","","11","1","1","89.3","9","8","中田貴士","55","ダ1230","","良","**","1:22.8","2.0","**","","","","","5-5-6-6","","40.4","444(+2)","","","ケープアグラス",""],"source":"netkeiba","surface":"ダ","time":"1:22.8","track_condition":"良","weather":"晴","winner_or_runner_up":"40.4"}},{"source":"netkeiba","race_date":"2024/09/12","meeting":"園田","weather":"晴","race_no":9,"race_name":"C2","race_id":"202450091209","race_url":"https://db.netkeiba.com/race/202450091209/","field_size":12,"bracket":3,"horse_number":3,"odds":88.8,"popularity":9,"finish":7,"jockey":"鴨宮祥行","carried_weight":55.0,"surface":"ダ","distance":"ダ1230","distance_m":1230,"track_condition":"良","time":"1:21.8","margin":"1.4","corners":"","pace":"","last_3f":null,"body_weight":"","winner_or_runner_up":"40.7","prize":null,"data":{"body_weight":"","bracket":3,"carried_weight":55.0,"corners":"","distance":"ダ1230","distance_m":1230,"field_size":12,"finish":7,"horse_id":348,"horse_name":"ショウナンマントル","horse_number":3,"jockey":"鴨宮祥行","last_3f":null,"margin":"1.4","meeting":"園田","netkeiba_id":"2021101042","odds":88.8,"pace":"","popularity":9,"prize":null,"race_date":"2024/09/12","race_id":"202450091209","race_name":"C2","race_no":9,"race_url":"https://db.netkeiba.com/race/202450091209/","raw":["2024/09/12","園田","晴","9","C2","","12","3","3","88.8","9","7","鴨宮祥行","55","ダ1230","","良","**","1:21.8","1.4","**","","","","","8-8-10-7","","40.7","442(+2)","","","ヨシノタルマエ",""],"source":"netkeiba","surface":"ダ","time":"1:21.8","track_condition":"良","weather":"晴","winner_or_runner_up":"40.7"}},{"source":"netkeiba","race_date":"2024/08/29","meeting":"園田","weather":"曇","race_no":8,"race_name":"C2二","race_id":"202450082908","race_url":"https://db.netkeiba.com/race/202450082908/","field_size":9,"bracket":8,"horse_number":9,"odds":43.5,"popularity":7,"finish":5,"jockey":"中田貴士","carried_weight":55.0,"surface":"ダ","distance":"ダ1400","distance_m":1400,"track_condition":"重","time":"1:35.1","margin":"0.9","corners":"","pace":"","last_3f":null,"body_weight":"","winner_or_runner_up":"42.8","prize":null,"data":{"body_weight":"","bracket":8,"carried_weight":55.0,"corners":"","distance":"ダ1400","distance_m":1400,"field_size":9,"finish":5,"horse_id":348,"horse_name":"ショウナンマントル","horse_number":9,"jockey":"中田貴士","last_3f":null,"margin":"0.9","meeting":"園田","netkeiba_id":"2021101042","odds":43.5,"pace":"","popularity":7,"prize":null,"race_date":"2024/08/29","race_id":"202450082908","race_name":"C2二","race_no":8,"race_url":"https://db.netkeiba.com/race/202450082908/","raw":["2024/08/29","園田","曇","8","C2二","","9","8","9","43.5","7","5","中田貴士","55","ダ1400","","重","**","1:35.1","0.9","**","","","","","5-5-2-2","","42.8","440(+11)","","","テイケイアンジェ","7.0"],"source":"netkeiba","surface":"ダ","time":"1:35.1","track_condition":"重","weather":"曇","winner_or_runner_up":"42.8"}},{"source":"netkeiba","race_date":"2024/08/07","meeting":"名古屋","weather":"晴","race_no":7,"race_name":"3歳3組","race_id":"202448080707","race_url":"https://db.netkeiba.com/race/202448080707/","field_size":11,"bracket":6,"horse_number":7,"odds":54.4,"popularity":10,"finish":9,"jockey":"山田祥雄","carried_weight":56.0,"surface":"ダ","distance":"ダ1500","distance_m":1500,"track_condition":"良","time":"1:39.8","margin":"2.9","corners":"","pace":"","last_3f":null,"body_weight":"","winner_or_runner_up":"42.4","prize":null,"data":{"body_weight":"","bracket":6,"carried_weight":56.0,"corners":"","distance":"ダ1500","distance_m":1500,"field_size":11,"finish":9,"horse_id":348,"horse_name":"ショウナンマントル","horse_number":7,"jockey":"山田祥雄","last_3f":null,"margin":"2.9","meeting":"名古屋","netkeiba_id":"2021101042","odds":54.4,"pace":"","popularity":10,"prize":null,"race_date":"2024/08/07","race_id":"202448080707","race_name":"3歳3組","race_no":7,"race_url":"https://db.netkeiba.com/race/202448080707/","raw":["2024/08/07","名古屋","晴","7","3歳3組","","11","6","7","54.4","10","9","山田祥雄","56","ダ1500","","良","**","1:39.8","2.9","**","","","","","3-3-6","","42.4","429(-6)","","","ハクサンソヌス",""],"source":"netkeiba","surface":"ダ","time":"1:39.8","track_condition":"良","weather":"晴","winner_or_runner_up":"42.4"}},{"source":"netkeiba","race_date":"2024/07/24","meeting":"名古屋","weather":"曇","race_no":4,"race_name":"3歳5組","race_id":"202448072404","race_url":"https://db.netkeiba.com/race/202448072404/","field_size":12,"bracket":7,"horse_number":9,"odds":3.5,"popularity":2,"finish":10,"jockey":"塚本征吾","carried_weight":56.0,"surface":"ダ","distance":"ダ1500","distance_m":1500,"track_condition":"良","time":"1:38.8","margin":"1.7","corners":"","pace":"","last_3f":null,"body_weight":"","winner_or_runner_up":"41.3","prize":null,"data":{"body_weight":"","bracket":7,"carried_weight":56.0,"corners":"","distance":"ダ1500","distance_m":1500,"field_size":12,"finish":10,"horse_id":348,"horse_name":"ショウナンマントル","horse_number":9,"jockey":"塚本征吾","last_3f":null,"margin":"1.7","meeting":"名古屋","netkeiba_id":"2021101042","odds":3.5,"pace":"","popularity":2,"prize":null,"race_date":"2024/07/24","race_id":"202448072404","race_name":"3歳5組","race_no":4,"race_url":"https://db.netkeiba.com/race/202448072404/","raw":["2024/07/24","名古屋","曇","4","3歳5組","","12","7","9","3.5","2","10","塚本征吾","56","ダ1500","","良","**","1:38.8","1.7","**","","","","","7-7-8","","41.3","435(-2)","","","ギースバッハ",""],"source":"netkeiba","surface":"ダ","time":"1:38.8","track_condition":"良","weather":"曇","winner_or_runner_up":"41.3"}},{"source":"netkeiba","race_date":"2024/07/10","meeting":"名古屋","weather":"曇","race_no":8,"race_name":"3歳3組","race_id":"202448071008","race_url":"https://db.netkeiba.com/race/202448071008/","field_size":12,"bracket":5,"horse_number":5,"odds":19.6,"popularity":5,"finish":6,"jockey":"加藤聡一","carried_weight":56.0,"surface":"ダ","distance":"ダ1500","distance_m":1500,"track_condition":"稍","time":"1:37.4","margin":"1.7","corners":"","pace":"","last_3f":null,"body_weight":"","winner_or_runner_up":"41.0","prize":null,"data":{"body_weight":"","bracket":5,"carried_weight":56.0,"corners":"","distance":"ダ1500","distance_m":1500,"field_size":12,"finish":6,"horse_id":348,"horse_name":"ショウナンマントル","horse_number":5,"jockey":"加藤聡一","last_3f":null,"margin":"1.7","meeting":"名古屋","netkeiba_id":"2021101042","odds":19.6,"pace":"","popularity":5,"prize":null,"race_date":"2024/07/10","race_id":"202448071008","race_name":"3歳3組","race_no":8,"race_url":"https://db.netkeiba.com/race/202448071008/","raw":["2024/07/10","名古屋","曇","8","3歳3組","","12","5","5","19.6","5","6","加藤聡一","56","ダ1500","","稍","**","1:37.4","1.7","**","","","","","1-1-5","","41.0","437(0)","","","エスタボニート",""],"source":"netkeiba","surface":"ダ","time":"1:37.4","track_condition":"稍","weather":"曇","winner_or_runner_up":"41.0"}},{"source":"netkeiba","race_date":"2024/06/26","meeting":"名古屋","weather":"曇","race_no":6,"race_name":"3歳3組","race_id":"202448062606","race_url":"https://db.netkeiba.com/race/202448062606/","field_size":12,"bracket":1,"horse_number":1,"odds":3.7,"popularity":2,"finish":8,"jockey":"塚本征吾","carried_weight":56.0,"surface":"ダ","distance":"ダ1500","distance_m":1500,"track_condition":"良","time":"1:38.2","margin":"1.1","corners":"","pace":"","last_3f":null,"body_weight":"","winner_or_runner_up":"41.1","prize":null,"data":{"body_weight":"","bracket":1,"carried_weight":56.0,"corners":"","distance":"ダ1500","distance_m":1500,"field_size":12,"finish":8,"horse_id":348,"horse_name":"ショウナンマントル","horse_number":1,"jockey":"塚本征吾","last_3f":null,"margin":"1.1","meeting":"名古屋","netkeiba_id":"2021101042","odds":3.7,"pace":"","popularity":2,"prize":null,"race_date":"2024/06/26","race_id":"202448062606","race_name":"3歳3組","race_no":6,"race_url":"https://db.netkeiba.com/race/202448062606/","raw":["2024/06/26","名古屋","曇","6","3歳3組","","12","1","1","3.7","2","8","塚本征吾","56","ダ1500","","良","**","1:38.2","1.1","**","","","","","1-1-2","","41.1","437(+7)","","","スキルハンター",""],"source":"netkeiba","surface":"ダ","time":"1:38.2","track_condition":"良","weather":"曇","winner_or_runner_up":"41.1"}},{"source":"netkeiba","race_date":"2024/05/25","meeting":"3京都11","weather":"晴","race_no":5,"race_name":"3歳未勝利","race_id":"202408031105","race_url":"https://db.netkeiba.com/race/202408031105/","field_size":17,"bracket":3,"horse_number":5,"odds":287.0,"popularity":14,"finish":16,"jockey":"角田大河","carried_weight":56.0,"surface":"芝","distance":"芝1800","distance_m":1800,"track_condition":"良","time":"1:48.5","margin":"2.9","corners":"**","pace":"**","last_3f":null,"body_weight":"**","winner_or_runner_up":"38.1","prize":null,"data":{"body_weight":"**","bracket":3,"carried_weight":56.0,"corners":"**","distance":"芝1800","distance_m":1800,"field_size":17,"finish":16,"horse_id":348,"horse_name":"ショウナンマントル","horse_number":5,"jockey":"角田大河","last_3f":null,"margin":"2.9","meeting":"3京都11","netkeiba_id":"2021101042","odds":287.0,"pace":"**","popularity":14,"prize":null,"race_date":"2024/05/25","race_id":"202408031105","race_name":"3歳未勝利","race_no":5,"race_url":"https://db.netkeiba.com/race/202408031105/","raw":["2024/05/25","3京都11","晴","5","3歳未勝利","","17","3","5","287.0","14","16","角田大河","56","芝1800","","良","**","1:48.5","2.9","**","**","**","**","**","2-2","34.3-35.3","38.1","430(+2)","","","アンジョルラス",""],"source":"netkeiba","surface":"芝","time":"1:48.5","track_condition":"良","weather":"晴","winner_or_runner_up":"38.1"}},{"source":"netkeiba","race_date":"2024/04/20","meeting":"2東京1","weather":"晴","race_no":5,"race_name":"3歳未勝利","race_id":"202405020105","race_url":"https://db.netkeiba.com/race/202405020105/","field_size":18,"bracket":4,"horse_number":8,"odds":315.8,"popularity":12,"finish":17,"jockey":"長浜鴻緒","carried_weight":54.0,"surface":"芝","distance":"芝1600","distance_m":1600,"track_condition":"良","time":"1:36.0","margin":"2.4","corners":"**","pace":"**","last_3f":null,"body_weight":"**","winner_or_runner_up":"37.3","prize":null,"data":{"body_weight":"**","bracket":4,"carried_weight":54.0,"corners":"**","distance":"芝1600","distance_m":1600,"field_size":18,"finish":17,"horse_id":348,"horse_name":"ショウナンマントル","horse_number":8,"jockey":"長浜鴻緒","last_3f":null,"margin":"2.4","meeting":"2東京1","netkeiba_id":"2021101042","odds":315.8,"pace":"**","popularity":12,"prize":null,"race_date":"2024/04/20","race_id":"202405020105","race_name":"3歳未勝利","race_no":5,"race_url":"https://db.netkeiba.com/race/202405020105/","raw":["2024/04/20","2東京1","晴","5","3歳未勝利","","18","4","8","315.8","12","17","長浜鴻緒","54","芝1600","","良","**","1:36.0","2.4","**","**","**","**","**","2-2","34.9-35.0","37.3","428(-4)","","","ジーゲル",""],"source":"netkeiba","surface":"芝","time":"1:36.0","track_condition":"良","weather":"晴","winner_or_runner_up":"37.3"}},{"source":"netkeiba","race_date":"2024/03/23","meeting":"1中京5","weather":"雨","race_no":4,"race_name":"3歳未勝利","race_id":"202407010504","race_url":"https://db.netkeiba.com/race/202407010504/","field_size":16,"bracket":5,"horse_number":9,"odds":214.6,"popularity":14,"finish":15,"jockey":"松本大輝","carried_weight":56.0,"surface":"芝","distance":"芝1600","distance_m":1600,"track_condition":"重","time":"1:39.6","margin":"3.2","corners":"**","pace":"**","last_3f":null,"body_weight":"**","winner_or_runner_up":"39.5","prize":null,"data":{"body_weight":"**","bracket":5,"carried_weight":56.0,"corners":"**","distance":"芝1600","distance_m":1600,"field_size":16,"finish":15,"horse_id":348,"horse_name":"ショウナンマントル","horse_number":9,"jockey":"松本大輝","last_3f":null,"margin":"3.2","meeting":"1中京5","netkeiba_id":"2021101042","odds":214.6,"pace":"**","popularity":14,"prize":null,"race_date":"2024/03/23","race_id":"202407010504","race_name":"3歳未勝利","race_no":4,"race_url":"https://db.netkeiba.com/race/202407010504/","raw":["2024/03/23","1中京5","雨","4","3歳未勝利","","16","5","9","214.6","14","15","松本大輝","56","芝1600","","重","**","1:39.6","3.2","**","**","**","**","**","3-3-4","35.6-36.8","39.5","432(-22)","","","グランエシェゾー",""],"source":"netkeiba","surface":"芝","time":"1:39.6","track_condition":"重","weather":"雨","winner_or_runner_up":"39.5"}},{"source":"netkeiba","race_date":"2023/12/23","meeting":"5阪神7","weather":"晴","race_no":3,"race_name":"2歳未勝利","race_id":"202309050703","race_url":"https://db.netkeiba.com/race/202309050703/","field_size":16,"bracket":1,"horse_number":2,"odds":134.4,"popularity":13,"finish":15,"jockey":"角田大河","carried_weight":55.0,"surface":"ダ","distance":"ダ1400","distance_m":1400,"track_condition":"良","time":"1:29.4","margin":"3.7","corners":"","pace":"","last_3f":null,"body_weight":"","winner_or_runner_up":"40.2","prize":null,"data":{"body_weight":"","bracket":1,"carried_weight":55.0,"corners":"","distance":"ダ1400","distance_m":1400,"field_size":16,"finish":15,"horse_id":348,"horse_name":"ショウナンマントル","horse_number":2,"jockey":"角田大河","last_3f":null,"margin":"3.7","meeting":"5阪神7","netkeiba_id":"2021101042","odds":134.4,"pace":"","popularity":13,"prize":null,"race_date":"2023/12/23","race_id":"202309050703","race_name":"2歳未勝利","race_no":3,"race_url":"https://db.netkeiba.com/race/202309050703/","raw":["2023/12/23","5阪神7","晴","3","2歳未勝利","","16","1","2","134.4","13","15","角田大河","55","ダ1400","","良","**","1:29.4","3.7","**","","","","","7-9","36.0-37.2","40.2","454(+4)","","","エートラックス",""],"source":"netkeiba","surface":"ダ","time":"1:29.4","track_condition":"良","weather":"晴","winner_or_runner_up":"40.2"}},{"source":"netkeiba","race_date":"2023/08/20","meeting":"2札幌4","weather":"曇","race_no":1,"race_name":"2歳未勝利","race_id":"202301020401","race_url":"https://db.netkeiba.com/race/202301020401/","field_size":11,"bracket":8,"horse_number":11,"odds":27.8,"popularity":6,"finish":11,"jockey":"池添謙一","carried_weight":55.0,"surface":"芝","distance":"芝1500","distance_m":1500,"track_condition":"稍","time":"1:34.9","margin":"2.0","corners":"","pace":"","last_3f":null,"body_weight":"","winner_or_runner_up":"40.1","prize":null,"data":{"body_weight":"","bracket":8,"carried_weight":55.0,"corners":"","distance":"芝1500","distance_m":1500,"field_size":11,"finish":11,"horse_id":348,"horse_name":"ショウナンマントル","horse_number":11,"jockey":"池添謙一","last_3f":null,"margin":"2.0","meeting":"2札幌4","netkeiba_id":"2021101042","odds":27.8,"pace":"","popularity":6,"prize":null,"race_date":"2023/08/20","race_id":"202301020401","race_name":"2歳未勝利","race_no":1,"race_url":"https://db.netkeiba.com/race/202301020401/","raw":["2023/08/20","2札幌4","曇","1","2歳未勝利","","11","8","11","27.8","6","11","池添謙一","55","芝1500","","稍","**","1:34.9","2.0","**","","","","","2-2-2","29.5-38.2","40.1","450(-6)","","","タイセイレスポンス",""],"source":"netkeiba","surface":"芝","time":"1:34.9","track_condition":"稍","weather":"曇","winner_or_runner_up":"40.1"}},{"source":"netkeiba","race_date":"2023/08/06","meeting":"1札幌6","weather":"雨","race_no":1,"race_name":"2歳未勝利","race_id":"202301010601","race_url":"https://db.netkeiba.com/race/202301010601/","field_size":14,"bracket":3,"horse_number":4,"odds":7.9,"popularity":5,"finish":6,"jockey":"池添謙一","carried_weight":55.0,"surface":"芝","distance":"芝1500","distance_m":1500,"track_condition":"重","time":"1:34.3","margin":"1.2","corners":"","pace":"","last_3f":null,"body_weight":"","winner_or_runner_up":"39.3","prize":null,"data":{"body_weight":"","bracket":3,"carried_weight":55.0,"corners":"","distance":"芝1500","distance_m":1500,"field_size":14,"finish":6,"horse_id":348,"horse_name":"ショウナンマントル","horse_number":4,"jockey":"池添謙一","last_3f":null,"margin":"1.2","meeting":"1札幌6","netkeiba_id":"2021101042","odds":7.9,"pace":"","popularity":5,"prize":null,"race_date":"2023/08/06","race_id":"202301010601","race_name":"2歳未勝利","race_no":1,"race_url":"https://db.netkeiba.com/race/202301010601/","raw":["2023/08/06","1札幌6","雨","1","2歳未勝利","","14","3","4","7.9","5","6","池添謙一","55","芝1500","","重","**","1:34.3","1.2","**","","","","","8-7-6","29.6-38.6","39.3","456(-2)","","","レーヴジーニアル",""],"source":"netkeiba","surface":"芝","time":"1:34.3","track_condition":"重","weather":"雨","winner_or_runner_up":"39.3"}},{"source":"netkeiba","race_date":"2023/06/24","meeting":"3阪神7","weather":"曇","race_no":1,"race_name":"2歳未勝利","race_id":"202309030701","race_url":"https://db.netkeiba.com/race/202309030701/","field_size":9,"bracket":3,"horse_number":3,"odds":3.1,"popularity":2,"finish":8,"jockey":"川田将雅","carried_weight":55.0,"surface":"芝","distance":"芝1600","distance_m":1600,"track_condition":"良","time":"1:38.2","margin":"3.1","corners":"","pace":"","last_3f":null,"body_weight":"","winner_or_runner_up":"39.3","prize":null,"data":{"body_weight":"","bracket":3,"carried_weight":55.0,"corners":"","distance":"芝1600","distance_m":1600,"field_size":9,"finish":8,"horse_id":348,"horse_name":"ショウナンマントル","horse_number":3,"jockey":"川田将雅","last_3f":null,"margin":"3.1","meeting":"3阪神7","netkeiba_id":"2021101042","odds":3.1,"pace":"","popularity":2,"prize":null,"race_date":"2023/06/24","race_id":"202309030701","race_name":"2歳未勝利","race_no":1,"race_url":"https://db.netkeiba.com/race/202309030701/","raw":["2023/06/24","3阪神7","曇","1","2歳未勝利","","9","3","3","3.1","2","8","川田将雅","55","芝1600","","良","**","1:38.2","3.1","**","","","","","5-4","34.9-37.2","39.3","458(-2)","","","フェンダー",""],"source":"netkeiba","surface":"芝","time":"1:38.2","track_condition":"良","weather":"曇","winner_or_runner_up":"39.3"}},{"source":"netkeiba","race_date":"2023/06/03","meeting":"3東京1","weather":"曇","race_no":5,"race_name":"2歳新馬","race_id":"202305030105","race_url":"https://db.netkeiba.com/race/202305030105/","field_size":9,"bracket":6,"horse_number":6,"odds":4.5,"popularity":2,"finish":2,"jockey":"戸崎圭太","carried_weight":55.0,"surface":"芝","distance":"芝1600","distance_m":1600,"track_condition":"不","time":"1:38.4","margin":"1.5","corners":"","pace":"","last_3f":null,"body_weight":"","winner_or_runner_up":"35.8","prize":null,"data":{"body_weight":"","bracket":6,"carried_weight":55.0,"corners":"","distance":"芝1600","distance_m":1600,"field_size":9,"finish":2,"horse_id":348,"horse_name":"ショウナンマントル","horse_number":6,"jockey":"戸崎圭太","last_3f":null,"margin":"1.5","meeting":"3東京1","netkeiba_id":"2021101042","odds":4.5,"pace":"","popularity":2,"prize":null,"race_date":"2023/06/03","race_id":"202305030105","race_name":"2歳新馬","race_no":5,"race_url":"https://db.netkeiba.com/race/202305030105/","raw":["2023/06/03","3東京1","曇","5","2歳新馬","","9","6","6","4.5","2","2","戸崎圭太","55","芝1600","","不","**","1:38.4","1.5","**","","","","","2-2","37.8-34.5","35.8","460(0)","","","シュトラウス","290.0"],"source":"netkeiba","surface":"芝","time":"1:38.4","track_condition":"不","weather":"曇","winner_or_runner_up":"35.8"}}],"stud":[]}