{"horse":{"id":561,"name":"エクシダス","sex":"セン","birth_year":2018,"birth_date":"2018年5月8日","color":"鹿毛","status":"セ","sire":"ドゥラメンテ","dam":"ヤマノサッシュ","broodmare_sire":"ファルブラヴ","bms_line":"Northern Dancer","female_family":"F1-t","imported_foundation_mare":"ロイヤルサツシユ(GB) ～","pedigree_crosses":"サンデーサイレンス(USA) ：S3×M3 ノーザンテースト(CAN) ：S5×M5","netkeiba_id":"2018100735","jbis_id":"0001267258","trainer":"池田忠好","affiliation":"(佐 賀)","trainer_region":"地方","owner":"光安慎一","breeder":"チャンピオンズファーム","birthplace":"新ひだか町","career_summary":"4戦0勝 [ 0-0-0-4 ]","major_win":"","earnings_netkeiba":1.6,"earnings_jbis":1.6,"last_race":"","last_finish":null,"hkjc_name_zh":null,"name_en":"Exodus","search_aliases":"Exodus","achievement_class":"未勝利","dam_birth_date":"2009-02-01","dam_birth_year":2009,"foal_birth_date":"2018-05-08","dam_age_at_foaling":9,"dam_age_precision":"exact","foal_order":1,"dam_netkeiba_id":"2009106534","dam_jbis_id":"0001108989","dam_career_summary":"2戦0勝 [ 0-0-0-2 ]","dam_earnings":0.0,"dam_major_win":null,"dam_known_foals":1,"dam_known_winners":0,"dam_known_graded_winners":0,"dam_siblings_json":"[]","dam_other_sire_foals_json":"[]","dam_metadata_source":"https://db.netkeiba.com/horse/2009106534/","dam_metadata_status":"profile_fetched","owner_id":"196030","owner_color_url":null,"dam_biological_parity":6,"dam_registered_foal_order":5,"dam_covering_sequence":null,"parity_confidence":"high","parity_source_url":"https://www.studbook.jp/users/ja/SearchBameiList?initial_forward=%E3%83%A4%E3%83%9E%E3%83%8E%E3%82%B5%E3%83%83%E3%82%B7%E3%83%A5&submit=%E9%A6%AC%E5%90%8D%E6%A4%9C%E7%B4%A2","dam_parity_basis":"biological_and_registered","parity_source_name":"Japan Stud Book"},"sources":[{"source":"jbis","source_horse_id":"0001267258","url":"https://www.jbis.or.jp/horse/0001267258/","fetched_at":"2026-07-06T04:11:20.549323+00:00","data":{"affiliation":"(佐 賀)","birth_year":2018,"breeder":"チャンピオンズファーム","breeder_url":"https://www.jbis.or.jp/breeder/0000003374/","bucket":"2018","dam":"ヤマノサッシュ","dam_id":"0001108989","earnings":1.6,"horse_id":"0001267258","horse_url":"https://www.jbis.or.jp/horse/0001267258/","last_finish":null,"last_race":"","last_race_url":null,"name":"エクシダス","raw":["エクシダス","2018","セン","ヤマノサッシュ","池田 忠好 (佐 賀)","チャンピオンズファーム","1.6万円","",""],"sex":"セン","sire":"ドゥラメンテ","source":"jbis","source_url":"https://www.jbis.or.jp/horse/0001151936/sire/progeny/?year=2018&belong=0&sort=name&items=100&page=1&order=A","trainer":"池田 忠好"}},{"source":"netkeiba","source_horse_id":"2018100735","url":"https://db.netkeiba.com/horse/2018100735/","fetched_at":"2026-07-06T04:11:20.549323+00:00","data":{"affiliation":"地","birth_year":2018,"breeder":"チャンピオンズファーム","broodmare_sire":"ファルブラヴ","broodmare_sire_id":"1998190004","dam":"ヤマノサッシュ","dam_id":"2009106534","earnings":1.6,"horse_id":"2018100735","horse_url":"https://db.netkeiba.com/horse/2018100735/","name":"エクシダス","owner":"光安慎一","raw":["","エクシダス","セ","2018","[血] [掲] [写]","[地] 池田忠好","ドゥラメンテ [ ]","ヤマノサッシュ [ ]","ファルブラヴ [ ]","光安慎一","チャンピオンズファーム","1.6"],"sex":"セ","sire":"ドゥラメンテ","source":"netkeiba","source_url":"https://db.netkeiba.com/horse/list.html?sire_id=2012104511&range=all&page=29","trainer":"池田忠好"}}],"races":[{"source":"netkeiba","race_date":"2021/02/28","meeting":"佐賀","weather":"晴","race_no":1,"race_name":"3歳ー6組","race_id":"202155022801","race_url":"https://db.netkeiba.com/race/202155022801/","field_size":10,"bracket":6,"horse_number":6,"odds":14.0,"popularity":6,"finish":5,"jockey":"山口勲","carried_weight":56.0,"surface":"ダ","distance":"ダ1400","distance_m":1400,"track_condition":"重","time":"1:33.5","margin":"2.0","corners":"","pace":"","last_3f":null,"body_weight":"","winner_or_runner_up":"41.3","prize":null,"data":{"body_weight":"","bracket":6,"carried_weight":56.0,"corners":"","distance":"ダ1400","distance_m":1400,"field_size":10,"finish":5,"horse_id":561,"horse_name":"エクシダス","horse_number":6,"jockey":"山口勲","last_3f":null,"margin":"2.0","meeting":"佐賀","netkeiba_id":"2018100735","odds":14.0,"pace":"","popularity":6,"prize":null,"race_date":"2021/02/28","race_id":"202155022801","race_name":"3歳ー6組","race_no":1,"race_url":"https://db.netkeiba.com/race/202155022801/","raw":["2021/02/28","佐賀","晴","1","3歳ー6組","","10","6","6","14.0","6","5","山口勲","56","ダ1400","","重","2","1:33.5","2.0","18","","","","","2-2-2-4","","41.3","474(+16)","","","カシノネメシス","1.6"],"source":"netkeiba","surface":"ダ","time":"1:33.5","track_condition":"重","weather":"晴","winner_or_runner_up":"41.3"}},{"source":"netkeiba","race_date":"2020/11/28","meeting":"5阪神8","weather":"晴","race_no":3,"race_name":"2歳未勝利","race_id":"202009050803","race_url":"https://db.netkeiba.com/race/202009050803/","field_size":11,"bracket":8,"horse_number":11,"odds":306.5,"popularity":11,"finish":11,"jockey":"小崎綾也","carried_weight":55.0,"surface":"ダ","distance":"ダ1200","distance_m":1200,"track_condition":"良","time":"1:18.3","margin":"5.6","corners":"","pace":"","last_3f":null,"body_weight":"","winner_or_runner_up":"41.1","prize":null,"data":{"body_weight":"","bracket":8,"carried_weight":55.0,"corners":"","distance":"ダ1200","distance_m":1200,"field_size":11,"finish":11,"horse_id":561,"horse_name":"エクシダス","horse_number":11,"jockey":"小崎綾也","last_3f":null,"margin":"5.6","meeting":"5阪神8","netkeiba_id":"2018100735","odds":306.5,"pace":"","popularity":11,"prize":null,"race_date":"2020/11/28","race_id":"202009050803","race_name":"2歳未勝利","race_no":3,"race_url":"https://db.netkeiba.com/race/202009050803/","raw":["2020/11/28","5阪神8","晴","3","2歳未勝利","","11","8","11","306.5","11","11","小崎綾也","55","ダ1200","","良","**","1:18.3","5.6","**","","","","","11-11","35.7-37.0","41.1","458(-12)","","","エナジーロッソ",""],"source":"netkeiba","surface":"ダ","time":"1:18.3","track_condition":"良","weather":"晴","winner_or_runner_up":"41.1"}},{"source":"netkeiba","race_date":"2020/08/15","meeting":"2札幌1","weather":"晴","race_no":2,"race_name":"2歳未勝利","race_id":"202001020102","race_url":"https://db.netkeiba.com/race/202001020102/","field_size":10,"bracket":8,"horse_number":10,"odds":73.2,"popularity":8,"finish":9,"jockey":"落合玄太","carried_weight":54.0,"surface":"ダ","distance":"ダ1000","distance_m":1000,"track_condition":"不","time":"1:02.3","margin":"2.9","corners":"","pace":"","last_3f":null,"body_weight":"","winner_or_runner_up":"37.7","prize":null,"data":{"body_weight":"","bracket":8,"carried_weight":54.0,"corners":"","distance":"ダ1000","distance_m":1000,"field_size":10,"finish":9,"horse_id":561,"horse_name":"エクシダス","horse_number":10,"jockey":"落合玄太","last_3f":null,"margin":"2.9","meeting":"2札幌1","netkeiba_id":"2018100735","odds":73.2,"pace":"","popularity":8,"prize":null,"race_date":"2020/08/15","race_id":"202001020102","race_name":"2歳未勝利","race_no":2,"race_url":"https://db.netkeiba.com/race/202001020102/","raw":["2020/08/15","2札幌1","晴","2","2歳未勝利","","10","8","10","73.2","8","9","落合玄太","54","ダ1000","","不","**","1:02.3","2.9","**","","","","","7-8","35.4-35.6","37.7","470(0)","","","サノカポ",""],"source":"netkeiba","surface":"ダ","time":"1:02.3","track_condition":"不","weather":"晴","winner_or_runner_up":"37.7"}},{"source":"netkeiba","race_date":"2020/08/08","meeting":"1札幌5","weather":"曇","race_no":5,"race_name":"2歳新馬","race_id":"202001010505","race_url":"https://db.netkeiba.com/race/202001010505/","field_size":9,"bracket":4,"horse_number":4,"odds":16.8,"popularity":6,"finish":9,"jockey":"亀田温心","carried_weight":52.0,"surface":"芝","distance":"芝1200","distance_m":1200,"track_condition":"良","time":"1:12.3","margin":"2.4","corners":"","pace":"","last_3f":null,"body_weight":"","winner_or_runner_up":"37.4","prize":null,"data":{"body_weight":"","bracket":4,"carried_weight":52.0,"corners":"","distance":"芝1200","distance_m":1200,"field_size":9,"finish":9,"horse_id":561,"horse_name":"エクシダス","horse_number":4,"jockey":"亀田温心","last_3f":null,"margin":"2.4","meeting":"1札幌5","netkeiba_id":"2018100735","odds":16.8,"pace":"","popularity":6,"prize":null,"race_date":"2020/08/08","race_id":"202001010505","race_name":"2歳新馬","race_no":5,"race_url":"https://db.netkeiba.com/race/202001010505/","raw":["2020/08/08","1札幌5","曇","5","2歳新馬","","9","4","4","16.8","6","9","亀田温心","52","芝1200","","良","**","1:12.3","2.4","**","","","","","2-5","34.7-35.2","37.4","470(0)","","","テーオーメアリー",""],"source":"netkeiba","surface":"芝","time":"1:12.3","track_condition":"良","weather":"曇","winner_or_runner_up":"37.4"}}],"stud":[]}